{
  "keyword": "캡슐세제",
  "scan_id": 6035,
  "total_products": 40,
  "total_collected": 38519,
  "products": [
    {
      "ranking": 1,
      "pid": "8641935458",
      "name": "맘스럽 퍼팩트 캡슐세제 4챔버 파우치형 국산제조 8배 초고농축 4in1 대용량 실내건조",
      "collected": 2591
    },
    {
      "ranking": 2,
      "pid": "9131334002",
      "name": "퍼실 뉴 디스크 프로 플러스 캡슐세제",
      "collected": 1955
    },
    {
      "ranking": 3,
      "pid": "8687771994",
      "name": "허글리 8IN1 딥 클린 초고농축 캡슐 세탁세제 코튼캔디 향",
      "collected": 4059
    },
    {
      "ranking": 4,
      "pid": "8363764498",
      "name": "커클랜드시그니춰 울트라클린 캡슐세제",
      "collected": 2937
    },
    {
      "ranking": 5,
      "pid": "7826482313",
      "name": "맘스럽 울트라 퍼퓸 캡슐세제 8배 초고농축 국내생산 프리미엄 3in1 대용량 실내건조형",
      "collected": 3859
    },
    {
      "ranking": 6,
      "pid": "7871650750",
      "name": "부케가르니 딥 클린 초고농축 캡슐세제",
      "collected": 4897
    },
    {
      "ranking": 7,
      "pid": "8017545584",
      "name": "퍼실 디스크 캡슐세제 라벤더",
      "collected": 2743
    },
    {
      "ranking": 8,
      "pid": "8398153236",
      "name": "맘스럽 울트라 파우치 캡슐세제",
      "collected": 1862
    },
    {
      "ranking": 9,
      "pid": "9423143454",
      "name": "허니맘 캡슐세제 일반용량 2배 16g x 100개 세탁세제 일반용 드럼용 양재동꽃시장향",
      "collected": 309
    },
    {
      "ranking": 10,
      "pid": "9320430648",
      "name": "캡슐세제 리퀴드 대용량 120개입 고농축 실내건조 캡슐세탁세제",
      "collected": 688
    },
    {
      "ranking": 11,
      "pid": "7751239581",
      "name": "순수크린 옥시풀 라벤더 캡슐세제 올인원 100개입 8배고농축 실내건조용세제 프리미엄",
      "collected": 2027
    },
    {
      "ranking": 12,
      "pid": "8773610674",
      "name": "퍼실 디스크 엑스퍼트 실내건조 캡슐세제",
      "collected": 1956
    },
    {
      "ranking": 13,
      "pid": "9160602047",
      "name": "캡슐세제 리퀴드 4챔버 실내건조 캡슐 세탁 세제",
      "collected": 1168
    },
    {
      "ranking": 14,
      "pid": "6779041072",
      "name": "무궁화 파워브라이트 초고농축 캡슐세제 마일드비누향 약 180입 대용량 코스트코 판매 180개입",
      "collected": 359
    },
    {
      "ranking": 15,
      "pid": "8835684957",
      "name": "봉쥬르끌레어 캡슐세제 200개입 아쿠아블루 프랑스아로마오일향 국내생산 특대용량 고농축 실내건조 세탁세제 과탄산소다 함유",
      "collected": 751
    },
    {
      "ranking": 16,
      "pid": "8333319122",
      "name": "아이러브베베 딥큐 캡슐세제 샤르망부케향",
      "collected": 1058
    },
    {
      "ranking": 17,
      "pid": "8489499073",
      "name": "맘스럽 울트라 라벤더 캡슐세제 파우치형 프리미엄 국내생산 특대용량 초고농축 실내건조형 일반겸용",
      "collected": 2589
    },
    {
      "ranking": 18,
      "pid": "9314455665",
      "name": "슈퍼딥큐 캡슐세제 오션브리즈 100개입 4팩(총 400개입) 대용량 고농축 드럼 일반 겸용",
      "collected": 8
    },
    {
      "ranking": 19,
      "pid": "8924481088",
      "name": "갓성비 슈퍼딥큐 캡슐세제 플라워코튼향",
      "collected": 1303
    },
    {
      "ranking": 20,
      "pid": "9172062740",
      "name": "캡슐세제 리퀴드 200개입 캡슐세탁세제 실내건조 캡슐 세제",
      "collected": 934
    },
    {
      "ranking": 21,
      "pid": "9245917269",
      "name": "슈퍼딥큐 포레스트 100개입 캡슐세제 고농축 세탁 실내건조 드럼 일반겸용",
      "collected": 27
    },
    {
      "ranking": 22,
      "pid": "6149126658",
      "name": "탑스텝 고농축 트리플 캡술세제 드럼 일반겸용 세탁세제",
      "collected": 293
    },
    {
      "ranking": 23,
      "pid": "8710604087",
      "name": "테크 딥클린 초고농축 캡슐세제",
      "collected": 146
    },
    {
      "ranking": 24,
      "pid": "8814763846",
      "name": "비트 라벤더 클린 캡슐 세제",
      "collected": 0
    },
    {
      "ranking": 25,
      "pid": "8863130163",
      "name": "워시테라피 캡슐세제 파우치형",
      "collected": 0
    },
    {
      "ranking": 26,
      "pid": "8769278546",
      "name": "액츠 멀티 솔루션 실내건조 컴팩트 캡슐세제",
      "collected": 0
    },
    {
      "ranking": 27,
      "pid": "8371659568",
      "name": "비트 울트라 콤팩트 캡슐세제 일반/드럼겸용 스위트블로썸향",
      "collected": 0
    },
    {
      "ranking": 28,
      "pid": "7986577736",
      "name": "잔류세제 걱정 없는 4 in1 고농축 캡슐 세탁세제 워시테라피 10g X 50개입",
      "collected": 0
    },
    {
      "ranking": 29,
      "pid": "6581568462",
      "name": "퍼실 디스크 캡슐세제 54개입 대용량 코스트코",
      "collected": 0
    },
    {
      "ranking": 30,
      "pid": "8505675833",
      "name": "파워크린 캡슐세탁세제 10gX50개입 드럼/일반 겸용 12배 초고농축 5in1 99.9% 항균",
      "collected": 0
    },
    {
      "ranking": 31,
      "pid": "8173755589",
      "name": "퍼실 디스크 컬러 캡슐세제",
      "collected": 0
    },
    {
      "ranking": 32,
      "pid": "8032055401",
      "name": "슈퍼큐 플라워 코튼 실내건조 고농축 대용량 캡슐세제",
      "collected": 0
    },
    {
      "ranking": 33,
      "pid": "9375735989",
      "name": "캡슐세제 리퀴드 200개입 밀크코튼향 캡슐세탁세제 실내건조 캡슐 세제",
      "collected": 0
    },
    {
      "ranking": 34,
      "pid": "7341023665",
      "name": "해피홈 파워캡슐 세탁세제 트리플 로즈",
      "collected": 0
    },
    {
      "ranking": 35,
      "pid": "8765262530",
      "name": "맘스럽아토워시 프렌치 라벤더 캡슐세제 10배고농축 국내산기술력 특대용량 10중효소 실내건조형 세탁세제 섬유유연제",
      "collected": 0
    },
    {
      "ranking": 36,
      "pid": "8871293878",
      "name": "퍼실 뉴 디스크 파워 플러스 세탁세제 25g",
      "collected": 0
    },
    {
      "ranking": 37,
      "pid": "9366408465",
      "name": "아로퓸 5in1 퍼퓸 캡슐세제 30개입X2종(로즈가든+퓨어블라썸)",
      "collected": 0
    },
    {
      "ranking": 38,
      "pid": "8333319251",
      "name": "아이러브베베 딥큐 오션브리즈 캡슐세제",
      "collected": 0
    },
    {
      "ranking": 39,
      "pid": "9314107041",
      "name": "순수크린 옥시풀 딥클린 퍼퓸 캡슐세제",
      "collected": 0
    },
    {
      "ranking": 40,
      "pid": "9466023144",
      "name": "카렐르 다용도 고농축 6챔버 캡슐 세탁세제 딥 클렌징 캡슐 세제",
      "collected": 0
    }
  ]
}