{
 "product_id": "9423117914",
 "product_title": "센트올 실내탈취제 알로에향 화장실 담배 새집증후군 실내 집안 홀애비 옷장 냄새 제거",
 "review_count_listed": 191,
 "collected_count": 201,
 "rating_summary": {
  "averageRating": 4.9,
  "ratingCounts": {
   "1": 0,
   "2": 0,
   "3": 7,
   "4": 9,
   "5": 185
  }
 },
 "reviews": [
  {
   "answer": "",
   "content": "진짜 아래층에 홀애비 살고 있는 듯...\n이게 도대체 무슨 냄새인지...\n\n냄새에 민감한 저에게 딱이네요.\n다른 타사 방향제 제품(뿌리고, 걸고)들은 향기가 너무 짙어서 사용불가...현관문 밖으로 쫓겨나 외부 냄새 물리치려고 두고, 이 제품으로 1개 시험삼아 구입했다가 딱 저한테 맞아 한개씩 두개씩, 금방은 4개 구매~냄새 나는 곳곳에 두려구요. 이 제품도 여러가지 중 이 제품이 저한테는 딱이네요. 은은한 꽃향~같기도하고~\n안좋은 냄새도 은은하게 물리쳐주네요~~^^",
   "created_at": "2026.05.19",
   "headline": "",
   "helpful_count": 0,
   "option": "센트올 실내탈취제 알로에향 화장실 담배 새집증후군 실내 집안 홀애비 옷장 냄새 제거, 300g, 2개",
   "photo_count": 0,
   "rating": 5,
   "user_name": "유*옥"
  },
  {
   "answer": "",
   "content": "신발장 냄새 때문에 스트레스였는데 이거 두고 나서 훨씬 나아졌어요! 향도 과하지 않아서 좋네요",
   "created_at": "2026.05.13",
   "headline": "",
   "helpful_count": 1,
   "option": "센트올 실내탈취제 알로에향 화장실 담배 새집증후군 실내 집안 홀애비 옷장 냄새 제거, 300g, 1개",
   "photo_count": 0,
   "rating": 5,
   "user_name": "손*은"
  },
  {
   "answer": "",
   "content": "베란다 쪽에서 올라오는 냄새 때문에 두어봤는데 며칠 지나니까 확실히 덜 느껴지네요! 생각보다 만족해요~",
   "created_at": "2026.05.13",
   "headline": "",
   "helpful_count": 0,
   "option": "센트올 실내탈취제 알로에향 화장실 담배 새집증후군 실내 집안 홀애비 옷장 냄새 제거, 300g, 1개",
   "photo_count": 0,
   "rating": 5,
   "user_name": "양*은"
  },
  {
   "answer": "",
   "content": "요리하고 난 뒤 거실에 두었는데 다음 날 냄새가 덜 남아있어서 신기했어요!",
   "created_at": "2026.05.13",
   "headline": "",
   "helpful_count": 0,
   "option": "센트올 실내탈취제 알로에향 화장실 담배 새집증후군 실내 집안 홀애비 옷장 냄새 제거, 300g, 1개",
   "photo_count": 0,
   "rating": 5,
   "user_name": "전*은"
  },
  {
   "answer": "",
   "content": "원룸이라 환기가 쉽지 않은데 방에 하나 두니까 훨씬 편하게 생활하고 있어요.",
   "created_at": "2026.05.02",
   "headline": "",
   "helpful_count": 0,
   "option": "센트올 실내탈취제 알로에향 화장실 담배 새집증후군 실내 집안 홀애비 옷장 냄새 제거, 300g, 1개",
   "photo_count": 0,
   "rating": 5,
   "user_name": "우*은"
  },
  {
   "answer": "",
   "content": "아이 있는 집이라 향 강한 제품은 피하는 편인데 이건 식물성 원료로 만들어지고 향도 은은해서 편하게 사용하고 있습니다!!",
   "created_at": "2026.05.02",
   "headline": "",
   "helpful_count": 0,
   "option": "센트올 실내탈취제 알로에향 화장실 담배 새집증후군 실내 집안 홀애비 옷장 냄새 제거, 300g, 1개",
   "photo_count": 0,
   "rating": 5,
   "user_name": "민*연"
  },
  {
   "answer": "",
   "content": "겨울철 같은 날씨에 환기 못하는 날에 특히 도움 되었어요 ㅎㅎ",
   "created_at": "2026.05.09",
   "headline": "",
   "helpful_count": 0,
   "option": "센트올 실내탈취제 알로에향 화장실 담배 새집증후군 실내 집안 홀애비 옷장 냄새 제거, 300g, 1개",
   "photo_count": 0,
   "rating": 5,
   "user_name": "허*린"
  },
  {
   "answer": "",
   "content": "고기 구운 날 거실에 뒀는데 다음 날 냄새 거의 안 남았어요 ㅎㅎ 이건 좀 놀랐어요~",
   "created_at": "2026.04.27",
   "headline": "",
   "helpful_count": 1,
   "option": "센트올 실내탈취제 알로에향 화장실 담배 새집증후군 실내 집안 홀애비 옷장 냄새 제거, 300g, 1개",
   "photo_count": 0,
   "rating": 5,
   "user_name": "박*은"
  },
  {
   "answer": "",
   "content": "방향제 냄새 싫어하는데 이건 부담 없이 쓸 수 있어서 만족합니다.",
   "created_at": "2026.05.02",
   "headline": "",
   "helpful_count": 0,
   "option": "센트올 실내탈취제 알로에향 화장실 담배 새집증후군 실내 집안 홀애비 옷장 냄새 제거, 300g, 1개",
   "photo_count": 0,
   "rating": 5,
   "user_name": "노*진"
  },
  {
   "answer": "",
   "content": "차 안에 두었는데 인위적인 향이 아니라서 오히려 더 좋네요 ㅎㅎ",
   "created_at": "2026.05.02",
   "headline": "",
   "helpful_count": 0,
   "option": "센트올 실내탈취제 알로에향 화장실 담배 새집증후군 실내 집안 홀애비 옷장 냄새 제거, 300g, 1개",
   "photo_count": 0,
   "rating": 5,
   "user_name": "주*현"
  },
  {
   "answer": "",
   "content": "화장실에 하수구 냄새가 너무 올라와서 머리가 아팠는데&hellip; 이거 하나 두니까 말도 안되게 악취들이 사라져서 너무 신기했어요&hellip;. 진짜 생활하는데 없어선 안될 꿀템인거 같아요!!",
   "created_at": "2026.03.26",
   "headline": "",
   "helpful_count": 3,
   "option": "센트올 실내탈취제 알로에향 화장실 담배 새집증후군 실내 집안 홀애비 옷장 냄새 제거, 300g, 1개",
   "photo_count": 0,
   "rating": 5,
   "user_name": "한*영"
  },
  {
   "answer": "",
   "content": "요즘 추워서 환기를 안시켰더니 방 안에 들어오면 이상한 냄새들이 나더라구요&hellip; 몇일 동안 테이블 위에 두었더니 방안에 냄새는 사라지고 공기가 좋아진 느낌이 들어요 ㅎㅎ",
   "created_at": "2026.03.26",
   "headline": "",
   "helpful_count": 0,
   "option": "센트올 실내탈취제 알로에향 화장실 담배 새집증후군 실내 집안 홀애비 옷장 냄새 제거, 300g, 1개",
   "photo_count": 0,
   "rating": 5,
   "user_name": "강*윤"
  },
  {
   "answer": "",
   "content": "비슷한 가격대 제품 사용해봤는데&hellip; 향이 진짜 머리가 아파서 방치해뒀는데 이건 은은해서 아직까지 잘 사용중이에요!!",
   "created_at": "2026.03.26",
   "headline": "",
   "helpful_count": 0,
   "option": "센트올 실내탈취제 알로에향 화장실 담배 새집증후군 실내 집안 홀애비 옷장 냄새 제거, 300g, 1개",
   "photo_count": 0,
   "rating": 5,
   "user_name": "류*유"
  },
  {
   "answer": "",
   "content": "알로에 느낌이라 그런지 진짜 깔끔해요! 인위적인 향 아니고 공기 정리되는 느낌이라 계속 두고 있어도 부담이 없네요  완전 만족!",
   "created_at": "2026.03.26",
   "headline": "",
   "helpful_count": 1,
   "option": "센트올 실내탈취제 알로에향 화장실 담배 새집증후군 실내 집안 홀애비 옷장 냄새 제거, 300g, 1개",
   "photo_count": 0,
   "rating": 5,
   "user_name": "신*빈"
  },
  {
   "answer": "",
   "content": "알로에 향이라 처음에는 별로일꺼라 생각했는데… 시간이 지나니까 향도 만족스럽고 탈취력도 좋아서 재구매 하려구요~",
   "created_at": "2026.03.26",
   "headline": "",
   "helpful_count": 0,
   "option": "센트올 실내탈취제 알로에향 화장실 담배 새집증후군 실내 집안 홀애비 옷장 냄새 제거, 300g, 1개",
   "photo_count": 0,
   "rating": 5,
   "user_name": "조*우"
  },
  {
   "answer": "",
   "content": "화장실에 두고 20분 지나니까 공기가 확 달라졌어요! 향으로 덮는 느낌이 아니라 깔끔해진 느낌이라 더 좋아요",
   "created_at": "2026.03.26",
   "headline": "",
   "helpful_count": 0,
   "option": "센트올 실내탈취제 알로에향 화장실 담배 새집증후군 실내 집안 홀애비 옷장 냄새 제거, 300g, 1개",
   "photo_count": 0,
   "rating": 5,
   "user_name": "송*우"
  },
  {
   "answer": "",
   "content": "향으로 덮는 느낌이 아니라 공간이 정리되는 느낌이에요. 알로에 특유의 산뜻함이 있어서 더 마음에 들어욧!",
   "created_at": "2026.03.26",
   "headline": "",
   "helpful_count": 0,
   "option": "센트올 실내탈취제 알로에향 화장실 담배 새집증후군 실내 집안 홀애비 옷장 냄새 제거, 300g, 1개",
   "photo_count": 0,
   "rating": 5,
   "user_name": "홍*서"
  },
  {
   "answer": "",
   "content": "알로에 향이라 그런지 시원하고 산뜻해요. 화학적인 느낌 전혀 없고, 오래 있어도 질리지 않아요!!",
   "created_at": "2026.03.26",
   "headline": "",
   "helpful_count": 0,
   "option": "센트올 실내탈취제 알로에향 화장실 담배 새집증후군 실내 집안 홀애비 옷장 냄새 제거, 300g, 1개",
   "photo_count": 0,
   "rating": 5,
   "user_name": "안*은"
  },
  {
   "answer": "",
   "content": "화장실 하수구 냄새 때문에 구매했는데 확실히 덜 올라오더라구요…. 향도 부담 없어서 좋아요 ㅎㅎ",
   "created_at": "2026.03.26",
   "headline": "",
   "helpful_count": 0,
   "option": "센트올 실내탈취제 알로에향 화장실 담배 새집증후군 실내 집안 홀애비 옷장 냄새 제거, 300g, 1개",
   "photo_count": 0,
   "rating": 5,
   "user_name": "전*빈"
  },
  {
   "answer": "",
   "content": "향에 예민한 편인데 이건 부담 없어요. 알로에 특유의 맑은 느낌이라 계속 두고 쓰기 좋아요!",
   "created_at": "2026.03.26",
   "headline": "",
   "helpful_count": 0,
   "option": "센트올 실내탈취제 알로에향 화장실 담배 새집증후군 실내 집안 홀애비 옷장 냄새 제거, 300g, 1개",
   "photo_count": 0,
   "rating": 5,
   "user_name": "손*현"
  },
  {
   "answer": "",
   "content": "침실에 강한 향 싫어서 고민했는데… 알로에 향이 자연적인 느낌이라 편해서 딱인거 같아요.",
   "created_at": "2026.03.26",
   "headline": "",
   "helpful_count": 0,
   "option": "센트올 실내탈취제 알로에향 화장실 담배 새집증후군 실내 집안 홀애비 옷장 냄새 제거, 300g, 1개",
   "photo_count": 0,
   "rating": 5,
   "user_name": "장*아"
  },
  {
   "answer": "",
   "content": "요리하고 나면 냄새 오래 갔는데 이거 두고 나서 확실히 빨리 빠져요~ 진작 쓸 걸 그랬어요!",
   "created_at": "2026.03.26",
   "headline": "",
   "helpful_count": 0,
   "option": "센트올 실내탈취제 알로에향 화장실 담배 새집증후군 실내 집안 홀애비 옷장 냄새 제거, 300g, 1개",
   "photo_count": 0,
   "rating": 5,
   "user_name": "조*은"
  },
  {
   "answer": "",
   "content": "뚜껑을 열자마자 알로에 향이 퍼져서 너무 좋았어요! 자연의 향기 같은 느낌이랄까?!",
   "created_at": "2026.03.26",
   "headline": "",
   "helpful_count": 0,
   "option": "센트올 실내탈취제 알로에향 화장실 담배 새집증후군 실내 집안 홀애비 옷장 냄새 제거, 300g, 1개",
   "photo_count": 0,
   "rating": 5,
   "user_name": "류*채"
  },
  {
   "answer": "",
   "content": "아이가 있는 집이라 제품을 고를 때 항상 보는게 성분이거든요&hellip; 식물성 원료로 만들었다고 해서 안심하고 사용하고 있습니다 ^^",
   "created_at": "2026.03.13",
   "headline": "",
   "helpful_count": 1,
   "option": "센트올 실내탈취제 알로에향 화장실 담배 새집증후군 실내 집안 홀애비 옷장 냄새 제거, 300g, 1개",
   "photo_count": 0,
   "rating": 5,
   "user_name": "송*은"
  },
  {
   "answer": "",
   "content": "여러 탈취제 브랜드 써봤는데… 센트올이 제일 만족스러웠어요. 알로에향 덕분인지 답답함 없이 산뜻해서 계속 찾게 됩니다 ㅎㅎ",
   "created_at": "2026.03.26",
   "headline": "",
   "helpful_count": 0,
   "option": "센트올 실내탈취제 알로에향 화장실 담배 새집증후군 실내 집안 홀애비 옷장 냄새 제거, 300g, 1개",
   "photo_count": 0,
   "rating": 5,
   "user_name": "박*은"
  },
  {
   "answer": "",
   "content": "아랫집에서 담배를 피는지.. 밤마다 담배냄새 때문에 스트레스 받았는데 배란다에 두니까 냄새들이 많이 사라졌더라구요&hellip;",
   "created_at": "2026.03.13",
   "headline": "",
   "helpful_count": 2,
   "option": "센트올 실내탈취제 알로에향 화장실 담배 새집증후군 실내 집안 홀애비 옷장 냄새 제거, 300g, 1개",
   "photo_count": 0,
   "rating": 5,
   "user_name": "오*은"
  },
  {
   "answer": "",
   "content": "처음엔 향이 약한가? 했는데 며칠 지나니까 확실히 달라졌어요. 냄새가 덜 올라와요! 이게 진짜 탈취인가 싶네요 ㅎㅎ",
   "created_at": "2026.03.26",
   "headline": "",
   "helpful_count": 0,
   "option": "센트올 실내탈취제 알로에향 화장실 담배 새집증후군 실내 집안 홀애비 옷장 냄새 제거, 300g, 1개",
   "photo_count": 0,
   "rating": 5,
   "user_name": "최*영"
  },
  {
   "answer": "",
   "content": "기숙사 방에서 쓰고 있는데 음식 냄새 스트레스가 줄었어요. 공간 작아서 그런지 체감도 빠른 편이에요.",
   "created_at": "2026.03.17",
   "headline": "",
   "helpful_count": 0,
   "option": "센트올 실내탈취제 알로에향 화장실 담배 새집증후군 실내 집안 홀애비 옷장 냄새 제거, 300g, 1개",
   "photo_count": 0,
   "rating": 5,
   "user_name": "문*은"
  },
  {
   "answer": "",
   "content": "화장실에 두고 나서부터 꿉꿉함이 확 줄었어요! 알로에 향 덕분인지 상쾌한 느낌이 오래 가더라구요",
   "created_at": "2026.03.26",
   "headline": "",
   "helpful_count": 0,
   "option": "센트올 실내탈취제 알로에향 화장실 담배 새집증후군 실내 집안 홀애비 옷장 냄새 제거, 300g, 1개",
   "photo_count": 0,
   "rating": 5,
   "user_name": "송*서"
  },
  {
   "answer": "",
   "content": "강한 향 싫어해서 언센티드로 골랐는데 완전 잘한 선택이에요. 향으로 덮는 느낌 아니라서 더 마음에 드네요~",
   "created_at": "2026.03.13",
   "headline": "",
   "helpful_count": 0,
   "option": "센트올 실내탈취제 알로에향 화장실 담배 새집증후군 실내 집안 홀애비 옷장 냄새 제거, 300g, 1개",
   "photo_count": 0,
   "rating": 5,
   "user_name": "이*유"
  },
  {
   "answer": "",
   "content": "향이 세지 않아서 아쉬운 분도 있을 듯. 저는 순한 게 좋아서 그냥저냥 만족해요",
   "created_at": "2026.03.13",
   "headline": "",
   "helpful_count": 0,
   "option": "센트올 실내탈취제 알로에향 화장실 담배 새집증후군 실내 집안 홀애비 옷장 냄새 제거, 300g, 1개",
   "photo_count": 0,
   "rating": 3,
   "user_name": "조*현"
  },
  {
   "answer": "",
   "content": "조금 더 강했으면 좋겠지만 은은한 알로에라 머리 안 아픈 건 장점입니다.",
   "created_at": "2026.03.13",
   "headline": "",
   "helpful_count": 0,
   "option": "센트올 실내탈취제 알로에향 화장실 담배 새집증후군 실내 집안 홀애비 옷장 냄새 제거, 300g, 1개",
   "photo_count": 0,
   "rating": 3,
   "user_name": "고*서"
  },
  {
   "answer": "",
   "content": "처음엔 잘 모르겠더니 조금씩 익숙해지네요. 무난하게 쓰기 좋아요!",
   "created_at": "2026.03.13",
   "headline": "",
   "helpful_count": 0,
   "option": "센트올 실내탈취제 알로에향 화장실 담배 새집증후군 실내 집안 홀애비 옷장 냄새 제거, 300g, 1개",
   "photo_count": 0,
   "rating": 3,
   "user_name": "허*인"
  },
  {
   "answer": "",
   "content": "차량용으론 살짝 약한 느낌? 그래도 향이 깔끔해서 괜찮아요",
   "created_at": "2026.03.13",
   "headline": "",
   "helpful_count": 0,
   "option": "센트올 실내탈취제 알로에향 화장실 담배 새집증후군 실내 집안 홀애비 옷장 냄새 제거, 300g, 1개",
   "photo_count": 0,
   "rating": 3,
   "user_name": "이*채"
  },
  {
   "answer": "",
   "content": "향은 약한 편인데 자극 없어서 좋네요. 계속 써보려구요!",
   "created_at": "2026.03.13",
   "headline": "",
   "helpful_count": 0,
   "option": "센트올 실내탈취제 알로에향 화장실 담배 새집증후군 실내 집안 홀애비 옷장 냄새 제거, 300g, 1개",
   "photo_count": 0,
   "rating": 3,
   "user_name": "문*은"
  },
  {
   "answer": "",
   "content": "악취 제거 관리용으로 괜찮은 제품 같아요.",
   "created_at": "2026.05.09",
   "headline": "",
   "helpful_count": 0,
   "option": "센트올 실내탈취제 알로에향 화장실 담배 새집증후군 실내 집안 홀애비 옷장 냄새 제거, 300g, 1개",
   "photo_count": 0,
   "rating": 3,
   "user_name": "백*현"
  },
  {
   "answer": "",
   "content": "처음엔 약한가 했는데 가까이 가면 알로에향이 은은하게 나요. 무난하게 쓰기 좋아요.",
   "created_at": "2026.03.26",
   "headline": "",
   "helpful_count": 0,
   "option": "센트올 실내탈취제 알로에향 화장실 담배 새집증후군 실내 집안 홀애비 옷장 냄새 제거, 300g, 1개",
   "photo_count": 0,
   "rating": 3,
   "user_name": "조*서"
  },
  {
   "answer": "",
   "content": "아직 사용한지 얼마 안되긴해서 잘모르겠지만… 탈취는 잘되는거 같아요.",
   "created_at": "2026.03.25",
   "headline": "",
   "helpful_count": 0,
   "option": "센트올 실내탈취제 알로에향 화장실 담배 새집증후군 실내 집안 홀애비 옷장 냄새 제거, 300g, 1개",
   "photo_count": 0,
   "rating": 4,
   "user_name": "송*현"
  },
  {
   "answer": "",
   "content": "아이방에 두려고 샀는데 알로에처럼 깨끗한 향이라 괜찮네요.",
   "created_at": "2026.03.26",
   "headline": "",
   "helpful_count": 0,
   "option": "센트올 실내탈취제 알로에향 화장실 담배 새집증후군 실내 집안 홀애비 옷장 냄새 제거, 300g, 1개",
   "photo_count": 0,
   "rating": 4,
   "user_name": "황*린"
  },
  {
   "answer": "",
   "content": "친구가 추천을 해줘서 구매해 봤는데 기대가 되네요~",
   "created_at": "2026.03.26",
   "headline": "",
   "helpful_count": 0,
   "option": "센트올 실내탈취제 알로에향 화장실 담배 새집증후군 실내 집안 홀애비 옷장 냄새 제거, 300g, 1개",
   "photo_count": 0,
   "rating": 4,
   "user_name": "윤*진"
  },
  {
   "answer": "",
   "content": "화장실에 두고 쓰는데 냄새가 덜 올라와요. 기대 이상이에요!",
   "created_at": "2026.03.17",
   "headline": "",
   "helpful_count": 0,
   "option": "센트올 실내탈취제 알로에향 화장실 담배 새집증후군 실내 집안 홀애비 옷장 냄새 제거, 300g, 1개",
   "photo_count": 0,
   "rating": 4,
   "user_name": "양*은"
  },
  {
   "answer": "",
   "content": "리뷰들이 좋아서 구매해봤어요! 사용해보고 후기 남겨볼게요 ㅎㅎ",
   "created_at": "2026.03.13",
   "headline": "",
   "helpful_count": 0,
   "option": "센트올 실내탈취제 알로에향 화장실 담배 새집증후군 실내 집안 홀애비 옷장 냄새 제거, 300g, 1개",
   "photo_count": 0,
   "rating": 4,
   "user_name": "송*은"
  },
  {
   "answer": "",
   "content": "음식 냄새 관리용으로 무난하게 잘 쓰고 있어요.",
   "created_at": "2026.03.15",
   "headline": "",
   "helpful_count": 0,
   "option": "센트올 실내탈취제 알로에향 화장실 담배 새집증후군 실내 집안 홀애비 옷장 냄새 제거, 300g, 1개",
   "photo_count": 0,
   "rating": 4,
   "user_name": "김*아"
  },
  {
   "answer": "",
   "content": "신발장 냄새 관리용으로 쓰는데 괜찮습니다.",
   "created_at": "2026.03.13",
   "headline": "",
   "helpful_count": 0,
   "option": "센트올 실내탈취제 알로에향 화장실 담배 새집증후군 실내 집안 홀애비 옷장 냄새 제거, 300g, 1개",
   "photo_count": 0,
   "rating": 4,
   "user_name": "박*채"
  },
  {
   "answer": "",
   "content": "",
   "created_at": "2026.05.02",
   "headline": "",
   "helpful_count": 0,
   "option": "센트올 실내탈취제 알로에향 화장실 담배 새집증후군 실내 집안 홀애비 옷장 냄새 제거, 300g, 1개",
   "photo_count": 0,
   "rating": 4,
   "user_name": "성*연"
  },
  {
   "answer": "",
   "content": "",
   "created_at": "2026.03.04",
   "headline": "",
   "helpful_count": 0,
   "option": "센트올 실내탈취제 알로에향 화장실 담배 새집증후군 실내 집안 홀애비 옷장 냄새 제거, 300g, 1개",
   "photo_count": 0,
   "rating": 4,
   "user_name": "박*은"
  },
  {
   "answer": "",
   "content": "반려동물 키우는 집이라 예민했는데 자극 없어서 너무 좋아요. 냄새만 깔끔하게 잡아줘서 계속 쓰게 되네요 ㅎㅎ",
   "created_at": "2026.03.13",
   "headline": "",
   "helpful_count": 0,
   "option": "센트올 실내탈취제 알로에향 화장실 담배 새집증후군 실내 집안 홀애비 옷장 냄새 제거, 300g, 1개",
   "photo_count": 0,
   "rating": 5,
   "user_name": "오*은"
  },
  {
   "answer": "",
   "content": "강한 탈취제 향 싫어하는 분들 많잖아요&hellip; 저도 그런데 이 제품은 딱 편안한 느낌이라 좋네요 ㅎㅎ",
   "created_at": "2026.03.13",
   "headline": "",
   "helpful_count": 0,
   "option": "센트올 실내탈취제 알로에향 화장실 담배 새집증후군 실내 집안 홀애비 옷장 냄새 제거, 300g, 1개",
   "photo_count": 0,
   "rating": 5,
   "user_name": "이*은"
  },
  {
   "answer": "",
   "content": "밖에 나갔다가 들어오면 알로에향이 잔잔하게 퍼져서 집안이 상쾌해진 기분이 들어용 ㅎㅎ",
   "created_at": "2026.03.26",
   "headline": "",
   "helpful_count": 0,
   "option": "센트올 실내탈취제 알로에향 화장실 담배 새집증후군 실내 집안 홀애비 옷장 냄새 제거, 300g, 1개",
   "photo_count": 0,
   "rating": 5,
   "user_name": "류*진"
  },
  {
   "answer": "",
   "content": "사무실에 두고 쓰는데 직원들이 향 좋다고 물어봐요 ㅋㅋ 근데 과하지 않아서 더 만족합니다!",
   "created_at": "2026.03.26",
   "headline": "",
   "helpful_count": 0,
   "option": "센트올 실내탈취제 알로에향 화장실 담배 새집증후군 실내 집안 홀애비 옷장 냄새 제거, 300g, 1개",
   "photo_count": 0,
   "rating": 5,
   "user_name": "허*은"
  },
  {
   "answer": "",
   "content": "집에 들어올 때마다 묘하게 나는 냄새 때문에 스트레스였는데 이거 두고 나서는 훨씬 편해졌어요!!",
   "created_at": "2026.03.13",
   "headline": "",
   "helpful_count": 0,
   "option": "센트올 실내탈취제 알로에향 화장실 담배 새집증후군 실내 집안 홀애비 옷장 냄새 제거, 300g, 1개",
   "photo_count": 0,
   "rating": 5,
   "user_name": "한*연"
  },
  {
   "answer": "",
   "content": "작은 매장에 두고 쓰는데 과하지 않아서 손님들도 좋아하셔서 기분이 좋았어요!",
   "created_at": "2026.03.26",
   "headline": "",
   "helpful_count": 0,
   "option": "센트올 실내탈취제 알로에향 화장실 담배 새집증후군 실내 집안 홀애비 옷장 냄새 제거, 300g, 1개",
   "photo_count": 0,
   "rating": 5,
   "user_name": "장*인"
  },
  {
   "answer": "",
   "content": "쓰레기 배출 전 냄새 때문에 스트레스였는데 다용도실에 두니까 훨씬 낫네요 ㅎㅎ",
   "created_at": "2026.03.26",
   "headline": "",
   "helpful_count": 0,
   "option": "센트올 실내탈취제 알로에향 화장실 담배 새집증후군 실내 집안 홀애비 옷장 냄새 제거, 300g, 1개",
   "photo_count": 0,
   "rating": 5,
   "user_name": "백*현"
  },
  {
   "answer": "",
   "content": "베란다 특유의 꿉꿉함이 줄었어요. 환기 안 되는 날에도 도움 되는 느낌이에요.",
   "created_at": "2026.03.26",
   "headline": "",
   "helpful_count": 0,
   "option": "센트올 실내탈취제 알로에향 화장실 담배 새집증후군 실내 집안 홀애비 옷장 냄새 제거, 300g, 1개",
   "photo_count": 0,
   "rating": 5,
   "user_name": "배*윤"
  },
  {
   "answer": "",
   "content": "강한 방향제 싫어하는 사람한테 딱이에요. 자연스러운 깨끗함이 포인트예요!",
   "created_at": "2026.03.26",
   "headline": "",
   "helpful_count": 0,
   "option": "센트올 실내탈취제 알로에향 화장실 담배 새집증후군 실내 집안 홀애비 옷장 냄새 제거, 300g, 1개",
   "photo_count": 0,
   "rating": 5,
   "user_name": "손*연"
  },
  {
   "answer": "",
   "content": "서재에서 오래된 냄새가 나서 넣어두었는데 20분정도 되니까 냄새가 싹 사라졌더라구요.. ㅎㅎ",
   "created_at": "2026.03.13",
   "headline": "",
   "helpful_count": 0,
   "option": "센트올 실내탈취제 알로에향 화장실 담배 새집증후군 실내 집안 홀애비 옷장 냄새 제거, 300g, 1개",
   "photo_count": 0,
   "rating": 5,
   "user_name": "손*진"
  },
  {
   "answer": "",
   "content": "신발장에 두고 효과 좋아서 화장실용으로 이번에는 언센티드로 사봤어요~",
   "created_at": "2026.03.26",
   "headline": "",
   "helpful_count": 0,
   "option": "센트올 실내탈취제 알로에향 화장실 담배 새집증후군 실내 집안 홀애비 옷장 냄새 제거, 300g, 1개",
   "photo_count": 0,
   "rating": 5,
   "user_name": "서*윤"
  },
  {
   "answer": "",
   "content": "현관 근처에 두었는데 집 냄새가 정리된 느낌이라 들어올 때 마다 기분이 좋아요~~",
   "created_at": "2026.03.15",
   "headline": "",
   "helpful_count": 0,
   "option": "센트올 실내탈취제 알로에향 화장실 담배 새집증후군 실내 집안 홀애비 옷장 냄새 제거, 300g, 1개",
   "photo_count": 0,
   "rating": 5,
   "user_name": "조*아"
  },
  {
   "answer": "",
   "content": "모래 냄새 때문에 고민이었는데 확 줄었어요. 반려동물 있는 집에 추천!",
   "created_at": "2026.03.26",
   "headline": "",
   "helpful_count": 0,
   "option": "센트올 실내탈취제 알로에향 화장실 담배 새집증후군 실내 집안 홀애비 옷장 냄새 제거, 300g, 1개",
   "photo_count": 0,
   "rating": 5,
   "user_name": "홍*윤"
  },
  {
   "answer": "",
   "content": "하부장 냄새 오래 갔는데 이거 하나로 정리됐어요. 생각보다 효과 좋네요",
   "created_at": "2026.03.25",
   "headline": "",
   "helpful_count": 0,
   "option": "센트올 실내탈취제 알로에향 화장실 담배 새집증후군 실내 집안 홀애비 옷장 냄새 제거, 300g, 1개",
   "photo_count": 0,
   "rating": 5,
   "user_name": "서*영"
  },
  {
   "answer": "",
   "content": "사무실에 두고 쓰는데 직원들 다 만족 중이에요 ㅎㅎ 향에 민감한 분들도 괜찮다고 하네요!!",
   "created_at": "2026.03.13",
   "headline": "",
   "helpful_count": 0,
   "option": "센트올 실내탈취제 알로에향 화장실 담배 새집증후군 실내 집안 홀애비 옷장 냄새 제거, 300g, 1개",
   "photo_count": 0,
   "rating": 5,
   "user_name": "한*경"
  },
  {
   "answer": "",
   "content": "탈취제 향이 부담 없어서 좋아요! 공기만 깔끔해진 느낌이라 계속 두고 쓰고 있습니다",
   "created_at": "2026.03.13",
   "headline": "",
   "helpful_count": 0,
   "option": "센트올 실내탈취제 알로에향 화장실 담배 새집증후군 실내 집안 홀애비 옷장 냄새 제거, 300g, 1개",
   "photo_count": 0,
   "rating": 5,
   "user_name": "홍*윤"
  },
  {
   "answer": "",
   "content": "다른 브랜드 쓰다가 다시 돌아왔어요. 결국 재구매는 센트올이네요 ㅋㅋㅋ",
   "created_at": "2026.03.26",
   "headline": "",
   "helpful_count": 0,
   "option": "센트올 실내탈취제 알로에향 화장실 담배 새집증후군 실내 집안 홀애비 옷장 냄새 제거, 300g, 1개",
   "photo_count": 0,
   "rating": 5,
   "user_name": "권*나"
  },
  {
   "answer": "",
   "content": "아들 방에 두니까 확실히 묵직한 냄새가 줄었어요. 은근 효과 좋네요!",
   "created_at": "2026.03.26",
   "headline": "",
   "helpful_count": 0,
   "option": "센트올 실내탈취제 알로에향 화장실 담배 새집증후군 실내 집안 홀애비 옷장 냄새 제거, 300g, 1개",
   "photo_count": 0,
   "rating": 5,
   "user_name": "배*아"
  },
  {
   "answer": "",
   "content": "제가 냄새에 예민한 편인데… 언센티드 향은 거슬리지 않아서 좋네요!",
   "created_at": "2026.03.26",
   "headline": "",
   "helpful_count": 0,
   "option": "센트올 실내탈취제 알로에향 화장실 담배 새집증후군 실내 집안 홀애비 옷장 냄새 제거, 300g, 1개",
   "photo_count": 0,
   "rating": 5,
   "user_name": "황*현"
  },
  {
   "answer": "",
   "content": "반려동물이 있어서 향 강한 제품은 싫었는데 향이 은은하게 나서 딱 좋은거 같아요~",
   "created_at": "2026.03.13",
   "headline": "",
   "helpful_count": 0,
   "option": "센트올 실내탈취제 알로에향 화장실 담배 새집증후군 실내 집안 홀애비 옷장 냄새 제거, 300g, 1개",
   "photo_count": 0,
   "rating": 5,
   "user_name": "손*훈"
  },
  {
   "answer": "",
   "content": "옷장에 쿰쿰한 냄새가 나서 넣어두었더니알로에 향이 퍼져서 산뜻한 느낌이네요!!",
   "created_at": "2026.03.13",
   "headline": "",
   "helpful_count": 0,
   "option": "센트올 실내탈취제 알로에향 화장실 담배 새집증후군 실내 집안 홀애비 옷장 냄새 제거, 300g, 1개",
   "photo_count": 0,
   "rating": 5,
   "user_name": "배*율"
  },
  {
   "answer": "",
   "content": "비교해보고 최종 선택했는데 후회 없어요. 계속 구매할 둣 합니다.",
   "created_at": "2026.03.26",
   "headline": "",
   "helpful_count": 0,
   "option": "센트올 실내탈취제 알로에향 화장실 담배 새집증후군 실내 집안 홀애비 옷장 냄새 제거, 300g, 1개",
   "photo_count": 0,
   "rating": 5,
   "user_name": "조*안"
  },
  {
   "answer": "",
   "content": "집에 화장실에 강한 방향제 향이 싫어서 여러 제품 찾아보다가 구매했는데 기대보다 좋습니다!! 은은해서 오래 두고 쓰기 편하네용~",
   "created_at": "2026.03.13",
   "headline": "",
   "helpful_count": 0,
   "option": "센트올 실내탈취제 알로에향 화장실 담배 새집증후군 실내 집안 홀애비 옷장 냄새 제거, 300g, 1개",
   "photo_count": 0,
   "rating": 5,
   "user_name": "강*은"
  },
  {
   "answer": "",
   "content": "욕실에서 쓰고 있는데 답답함이 덜해졌어요. 깔끔한 느낌이라 만족!",
   "created_at": "2026.03.15",
   "headline": "",
   "helpful_count": 0,
   "option": "센트올 실내탈취제 알로에향 화장실 담배 새집증후군 실내 집안 홀애비 옷장 냄새 제거, 300g, 1개",
   "photo_count": 0,
   "rating": 5,
   "user_name": "류*인"
  },
  {
   "answer": "",
   "content": "침실에 두고 자는데 큰 불편함이 없어서 너무 만족스러워요~",
   "created_at": "2026.03.26",
   "headline": "",
   "helpful_count": 0,
   "option": "센트올 실내탈취제 알로에향 화장실 담배 새집증후군 실내 집안 홀애비 옷장 냄새 제거, 300g, 1개",
   "photo_count": 0,
   "rating": 5,
   "user_name": "문*은"
  },
  {
   "answer": "",
   "content": "강한 방향제 쓰다 머리 아파서 바꿨는데 이건 편안해용 ^^ 은은한 게 최고네요",
   "created_at": "2026.03.13",
   "headline": "",
   "helpful_count": 0,
   "option": "센트올 실내탈취제 알로에향 화장실 담배 새집증후군 실내 집안 홀애비 옷장 냄새 제거, 300g, 1개",
   "photo_count": 0,
   "rating": 5,
   "user_name": "허*린"
  },
  {
   "answer": "",
   "content": "재구매하면서 집 곳곳에 배치했어요. 만족도 계속 유지 중",
   "created_at": "2026.03.26",
   "headline": "",
   "helpful_count": 0,
   "option": "센트올 실내탈취제 알로에향 화장실 담배 새집증후군 실내 집안 홀애비 옷장 냄새 제거, 300g, 1개",
   "photo_count": 0,
   "rating": 5,
   "user_name": "이*윤"
  },
  {
   "answer": "",
   "content": "알로에 특유의 은은함이 기분까지 편안하게 만들어줘요.",
   "created_at": "2026.03.26",
   "headline": ".",
   "helpful_count": 0,
   "option": "센트올 실내탈취제 알로에향 화장실 담배 새집증후군 실내 집안 홀애비 옷장 냄새 제거, 300g, 1개",
   "photo_count": 0,
   "rating": 5,
   "user_name": "전*은"
  },
  {
   "answer": "",
   "content": "냄새 잡으면서도 공기 자체가 산뜻해지는 느낌이에요.",
   "created_at": "2026.03.26",
   "headline": "",
   "helpful_count": 0,
   "option": "센트올 실내탈취제 알로에향 화장실 담배 새집증후군 실내 집안 홀애비 옷장 냄새 제거, 300g, 1개",
   "photo_count": 0,
   "rating": 5,
   "user_name": "임*원"
  },
  {
   "answer": "",
   "content": "여러 개 비교해보고 결정했는데 선택 잘한 것 같아요 ㅎㅎ",
   "created_at": "2026.03.26",
   "headline": "",
   "helpful_count": 0,
   "option": "센트올 실내탈취제 알로에향 화장실 담배 새집증후군 실내 집안 홀애비 옷장 냄새 제거, 300g, 1개",
   "photo_count": 0,
   "rating": 5,
   "user_name": "서*안"
  },
  {
   "answer": "",
   "content": "지인 선물하고 저도 또 구매했어요. 만족도가 높아요 ㅎㅎㅎ",
   "created_at": "2026.03.26",
   "headline": "",
   "helpful_count": 0,
   "option": "센트올 실내탈취제 알로에향 화장실 담배 새집증후군 실내 집안 홀애비 옷장 냄새 제거, 300g, 1개",
   "photo_count": 0,
   "rating": 5,
   "user_name": "안*주"
  },
  {
   "answer": "",
   "content": "다 쓰기도 전에 또 주문했어요! 이젠 집 필수템입니다 ㅎㅎ",
   "created_at": "2026.03.26",
   "headline": "",
   "helpful_count": 0,
   "option": "센트올 실내탈취제 알로에향 화장실 담배 새집증후군 실내 집안 홀애비 옷장 냄새 제거, 300g, 1개",
   "photo_count": 0,
   "rating": 5,
   "user_name": "윤*서"
  },
  {
   "answer": "",
   "content": "방에 두고 일주일 정도 써봤는데 꿉꿉한 냄새가 덜 나는 느낌이에용!",
   "created_at": "2026.03.13",
   "headline": "",
   "helpful_count": 0,
   "option": "센트올 실내탈취제 알로에향 화장실 담배 새집증후군 실내 집안 홀애비 옷장 냄새 제거, 300g, 1개",
   "photo_count": 0,
   "rating": 5,
   "user_name": "전*은"
  },
  {
   "answer": "",
   "content": "평소에 방향제 싫어하는 남편도 이건 괜찮다고 하네요 ㅋㅋ 성공!",
   "created_at": "2026.03.13",
   "headline": "",
   "helpful_count": 0,
   "option": "센트올 실내탈취제 알로에향 화장실 담배 새집증후군 실내 집안 홀애비 옷장 냄새 제거, 300g, 1개",
   "photo_count": 0,
   "rating": 5,
   "user_name": "홍*서"
  },
  {
   "answer": "",
   "content": "강한 방향제 쓰다가 센트올로 바꿨는데 집안 공기가 훨씬 깔끔합니다. 집 분위기까지 달라진 느낌이에요 ㅋㅋㅋ",
   "created_at": "2026.03.13",
   "headline": "",
   "helpful_count": 0,
   "option": "센트올 실내탈취제 알로에향 화장실 담배 새집증후군 실내 집안 홀애비 옷장 냄새 제거, 300g, 1개",
   "photo_count": 0,
   "rating": 5,
   "user_name": "조*은"
  },
  {
   "answer": "",
   "content": "알로에 계열이라 시원하고 깨끗한 느낌이에요. 여름에 특히 잘 어울릴꺼 같아요!",
   "created_at": "2026.03.15",
   "headline": "",
   "helpful_count": 0,
   "option": "센트올 실내탈취제 알로에향 화장실 담배 새집증후군 실내 집안 홀애비 옷장 냄새 제거, 300g, 1개",
   "photo_count": 0,
   "rating": 5,
   "user_name": "유*은"
  },
  {
   "answer": "",
   "content": "탈취제 특유의 향이 싫었는데 이건 진짜 깔끔해요. 덮는 느낌 전혀 없어요.",
   "created_at": "2026.03.17",
   "headline": "",
   "helpful_count": 0,
   "option": "센트올 실내탈취제 알로에향 화장실 담배 새집증후군 실내 집안 홀애비 옷장 냄새 제거, 300g, 1개",
   "photo_count": 0,
   "rating": 5,
   "user_name": "정*아"
  },
  {
   "answer": "",
   "content": "아이 쓰는 화장실이라 신경 쓰였는데 식물성 원료로 만들어져서 자극이 없어 마음 편해요.",
   "created_at": "2026.03.13",
   "headline": "",
   "helpful_count": 0,
   "option": "센트올 실내탈취제 알로에향 화장실 담배 새집증후군 실내 집안 홀애비 옷장 냄새 제거, 300g, 1개",
   "photo_count": 0,
   "rating": 5,
   "user_name": "임*윤"
  },
  {
   "answer": "",
   "content": "알로에 향이라 그런지 텁텁함이 없어요. 공간이 산뜻해진 느낌이라 만족해용!!",
   "created_at": "2026.03.15",
   "headline": "",
   "helpful_count": 0,
   "option": "센트올 실내탈취제 알로에향 화장실 담배 새집증후군 실내 집안 홀애비 옷장 냄새 제거, 300g, 1개",
   "photo_count": 0,
   "rating": 5,
   "user_name": "최*윤"
  },
  {
   "answer": "",
   "content": "아이방에 두고 쓰는데 부담 없는 향이라 너무 좋아요! 은은한 알로에 향이라 안심됩니다 ^ㅡ^",
   "created_at": "2026.03.13",
   "headline": "",
   "helpful_count": 0,
   "option": "센트올 실내탈취제 알로에향 화장실 담배 새집증후군 실내 집안 홀애비 옷장 냄새 제거, 300g, 1개",
   "photo_count": 0,
   "rating": 5,
   "user_name": "최*율"
  },
  {
   "answer": "",
   "content": "차량용으로 샀는데 에어컨 틀 때 올라오던 냄새가 줄었어요. 향도 부담 없어서 좋네요",
   "created_at": "2026.03.13",
   "headline": "",
   "helpful_count": 0,
   "option": "센트올 실내탈취제 알로에향 화장실 담배 새집증후군 실내 집안 홀애비 옷장 냄새 제거, 300g, 1개",
   "photo_count": 0,
   "rating": 5,
   "user_name": "임*빈"
  },
  {
   "answer": "",
   "content": "처음엔 약한가 했는데 가까이 가면 알로에향이 은은하게 나요. 무난하게 쓰기 좋아요.",
   "created_at": "2026.03.13",
   "headline": "",
   "helpful_count": 0,
   "option": "센트올 실내탈취제 알로에향 화장실 담배 새집증후군 실내 집안 홀애비 옷장 냄새 제거, 300g, 1개",
   "photo_count": 0,
   "rating": 5,
   "user_name": "조*서"
  },
  {
   "answer": "",
   "content": "화장실에 두고 20분 지나니까 차이가 느껴졌어요. 알로에 향 덕분에 더 산뜻해요.",
   "created_at": "2026.03.13",
   "headline": "",
   "helpful_count": 0,
   "option": "센트올 실내탈취제 알로에향 화장실 담배 새집증후군 실내 집안 홀애비 옷장 냄새 제거, 300g, 1개",
   "photo_count": 0,
   "rating": 5,
   "user_name": "조*현"
  },
  {
   "answer": "",
   "content": "부모님께 선물해 드렸더니 향도 좋고 탈취도 좋다고 만족스러워 하시니까 뿌듯하네요",
   "created_at": "2026.03.12",
   "headline": "",
   "helpful_count": 0,
   "option": "센트올 실내탈취제 알로에향 화장실 담배 새집증후군 실내 집안 홀애비 옷장 냄새 제거, 300g, 1개",
   "photo_count": 0,
   "rating": 5,
   "user_name": "백*은"
  },
  {
   "answer": "",
   "content": "신발장 열 때마다 스트레스였는데 요즘은 괜찮아요! 향이 과하지 않아서 더 만족쓰!",
   "created_at": "2026.03.13",
   "headline": "",
   "helpful_count": 0,
   "option": "센트올 실내탈취제 알로에향 화장실 담배 새집증후군 실내 집안 홀애비 옷장 냄새 제거, 300g, 1개",
   "photo_count": 0,
   "rating": 5,
   "user_name": "임*원"
  },
  {
   "answer": "",
   "content": "타사 고체 탈취제보다 확실히 부담이 덜해요. 향이 질리지 않은게 장점인거 같아요~",
   "created_at": "2026.03.13",
   "headline": "",
   "helpful_count": 0,
   "option": "센트올 실내탈취제 알로에향 화장실 담배 새집증후군 실내 집안 홀애비 옷장 냄새 제거, 300g, 1개",
   "photo_count": 0,
   "rating": 5,
   "user_name": "홍*아"
  },
  {
   "answer": "",
   "content": "반려동물 키우는데 식물성 원료로 되어 자극이 없어서 안심하고 사용중입니다.",
   "created_at": "2026.03.13",
   "headline": "",
   "helpful_count": 0,
   "option": "센트올 실내탈취제 알로에향 화장실 담배 새집증후군 실내 집안 홀애비 옷장 냄새 제거, 300g, 1개",
   "photo_count": 0,
   "rating": 5,
   "user_name": "임*진"
  },
  {
   "answer": "",
   "content": "무향인 줄 알았는데 살짝 알로에 느낌이 나요. 근데 부담 없는 향이라 오히려 더 좋아요 ㅎㅎ",
   "created_at": "2026.03.12",
   "headline": "",
   "helpful_count": 0,
   "option": "센트올 실내탈취제 알로에향 화장실 담배 새집증후군 실내 집안 홀애비 옷장 냄새 제거, 300g, 1개",
   "photo_count": 0,
   "rating": 5,
   "user_name": "오*아"
  },
  {
   "answer": "",
   "content": "무향인 줄 알았는데 살짝 알로에향이 나서 오히려 더 좋네요! 깔끔한 느낌입니다.",
   "created_at": "2026.03.13",
   "headline": "",
   "helpful_count": 0,
   "option": "센트올 실내탈취제 알로에향 화장실 담배 새집증후군 실내 집안 홀애비 옷장 냄새 제거, 300g, 1개",
   "photo_count": 0,
   "rating": 5,
   "user_name": "이*은"
  },
  {
   "answer": "",
   "content": "알로에향이라 그런지 공기가 부드러워진 느낌이에요. 생각보다 괜찮아서 놀람!",
   "created_at": "2026.03.13",
   "headline": "",
   "helpful_count": 0,
   "option": "센트올 실내탈취제 알로에향 화장실 담배 새집증후군 실내 집안 홀애비 옷장 냄새 제거, 300g, 1개",
   "photo_count": 0,
   "rating": 5,
   "user_name": "조*안"
  },
  {
   "answer": "",
   "content": "강한 향 좋아하는 분들에겐 약할 수도 있어요. 저는 나쁘지 않았어요",
   "created_at": "2026.03.15",
   "headline": "",
   "helpful_count": 0,
   "option": "센트올 실내탈취제 알로에향 화장실 담배 새집증후군 실내 집안 홀애비 옷장 냄새 제거, 300g, 1개",
   "photo_count": 0,
   "rating": 5,
   "user_name": "백*원"
  },
  {
   "answer": "",
   "content": "알로에 특유의 깨끗한 느낌! 화학적인 향이 아니라서 계속 맡고 있어도 편해요.",
   "created_at": "2026.03.13",
   "headline": "",
   "helpful_count": 0,
   "option": "센트올 실내탈취제 알로에향 화장실 담배 새집증후군 실내 집안 홀애비 옷장 냄새 제거, 300g, 1개",
   "photo_count": 0,
   "rating": 5,
   "user_name": "장*현"
  },
  {
   "answer": "",
   "content": "지인이 추천해줘서 구매해봤는데 생각보다 제 스탈이에영!!",
   "created_at": "2026.03.17",
   "headline": "",
   "helpful_count": 0,
   "option": "센트올 실내탈취제 알로에향 화장실 담배 새집증후군 실내 집안 홀애비 옷장 냄새 제거, 300g, 1개",
   "photo_count": 0,
   "rating": 5,
   "user_name": "문*은"
  },
  {
   "answer": "",
   "content": "처음엔 체감이 약했는데 시간이 지나니까 확실히 다르네요!",
   "created_at": "2026.03.17",
   "headline": "",
   "helpful_count": 0,
   "option": "센트올 실내탈취제 알로에향 화장실 담배 새집증후군 실내 집안 홀애비 옷장 냄새 제거, 300g, 1개",
   "photo_count": 0,
   "rating": 5,
   "user_name": "강*경"
  },
  {
   "answer": "",
   "content": "처음엔 별 차이 모르겠었는데 며칠 지나니까 확실히 다르네요&hellip;",
   "created_at": "2026.03.13",
   "headline": "",
   "helpful_count": 0,
   "option": "센트올 실내탈취제 알로에향 화장실 담배 새집증후군 실내 집안 홀애비 옷장 냄새 제거, 300g, 1개",
   "photo_count": 0,
   "rating": 5,
   "user_name": "서*린"
  },
  {
   "answer": "",
   "content": "향 예민한 편인데 머리 아픈 느낌 전혀 없어요. 은은해서 오래 둬도 편안합니다~",
   "created_at": "2026.03.13",
   "headline": "",
   "helpful_count": 0,
   "option": "센트올 실내탈취제 알로에향 화장실 담배 새집증후군 실내 집안 홀애비 옷장 냄새 제거, 300g, 1개",
   "photo_count": 0,
   "rating": 5,
   "user_name": "배*원"
  },
  {
   "answer": "",
   "content": "향이 강하지 않아서 좋네요. 은은한 제품 찾으셨다면 추천이에요",
   "created_at": "2026.03.15",
   "headline": "",
   "helpful_count": 0,
   "option": "센트올 실내탈취제 알로에향 화장실 담배 새집증후군 실내 집안 홀애비 옷장 냄새 제거, 300g, 1개",
   "photo_count": 0,
   "rating": 5,
   "user_name": "류*아"
  },
  {
   "answer": "",
   "content": "반려동물 있는 집인데 자극 없어서 편하게 쓰고 있습니다.",
   "created_at": "2026.03.17",
   "headline": "",
   "helpful_count": 0,
   "option": "센트올 실내탈취제 알로에향 화장실 담배 새집증후군 실내 집안 홀애비 옷장 냄새 제거, 300g, 1개",
   "photo_count": 0,
   "rating": 5,
   "user_name": "임*윤"
  },
  {
   "answer": "",
   "content": "냄새가 쌓이는 게 줄어든 느낌이라 계속 쓰게 되더라구요 ㅋㅋㅋ",
   "created_at": "2026.03.17",
   "headline": "",
   "helpful_count": 0,
   "option": "센트올 실내탈취제 알로에향 화장실 담배 새집증후군 실내 집안 홀애비 옷장 냄새 제거, 300g, 1개",
   "photo_count": 0,
   "rating": 5,
   "user_name": "백*현"
  },
  {
   "answer": "",
   "content": "탈취제 특유의 머리 아픈 향이 없어서 오래 두고 쓰기 딱이에요 ㅎㅎ",
   "created_at": "2026.03.15",
   "headline": "",
   "helpful_count": 0,
   "option": "센트올 실내탈취제 알로에향 화장실 담배 새집증후군 실내 집안 홀애비 옷장 냄새 제거, 300g, 1개",
   "photo_count": 0,
   "rating": 5,
   "user_name": "백*린"
  },
  {
   "answer": "",
   "content": "고체형이라 사용도 간편하고 흘릴 걱정 없어서 좋네요 ㅎㅎ",
   "created_at": "2026.03.17",
   "headline": "",
   "helpful_count": 0,
   "option": "센트올 실내탈취제 알로에향 화장실 담배 새집증후군 실내 집안 홀애비 옷장 냄새 제거, 300g, 1개",
   "photo_count": 0,
   "rating": 5,
   "user_name": "안*은"
  },
  {
   "answer": "",
   "content": "이 정도면 아이가 있는 집에서도 향이 은은해서 사용하기 좋은 것 같아요!",
   "created_at": "2026.03.13",
   "headline": "",
   "helpful_count": 0,
   "option": "센트올 실내탈취제 알로에향 화장실 담배 새집증후군 실내 집안 홀애비 옷장 냄새 제거, 300g, 1개",
   "photo_count": 0,
   "rating": 5,
   "user_name": "권*은"
  },
  {
   "answer": "",
   "content": "집에 손님 올 때 냄새 때문에 신경 쓰였는데 이제는 걱정이 줄었습니다.",
   "created_at": "2026.03.13",
   "headline": "",
   "helpful_count": 0,
   "option": "센트올 실내탈취제 알로에향 화장실 담배 새집증후군 실내 집안 홀애비 옷장 냄새 제거, 300g, 1개",
   "photo_count": 0,
   "rating": 5,
   "user_name": "신*윤"
  },
  {
   "answer": "",
   "content": "혼자 사는 분들&hellip; 원룸 필수템이에요 진짜&hellip;!!",
   "created_at": "2026.03.13",
   "headline": "",
   "helpful_count": 0,
   "option": "센트올 실내탈취제 알로에향 화장실 담배 새집증후군 실내 집안 홀애비 옷장 냄새 제거, 300g, 1개",
   "photo_count": 0,
   "rating": 5,
   "user_name": "오*안"
  },
  {
   "answer": "",
   "content": "산뜻한 향이 은근히 유지돼서 만족스러워서 주변에 추천해드렸어요 ㅎㅎ",
   "created_at": "2026.03.13",
   "headline": "",
   "helpful_count": 0,
   "option": "센트올 실내탈취제 알로에향 화장실 담배 새집증후군 실내 집안 홀애비 옷장 냄새 제거, 300g, 1개",
   "photo_count": 0,
   "rating": 5,
   "user_name": "유*우"
  },
  {
   "answer": "",
   "content": "사무실용으로 하나 더 구매했어요. 집에서 만족해서 바로 재구매 완료!",
   "created_at": "2026.03.13",
   "headline": "",
   "helpful_count": 0,
   "option": "센트올 실내탈취제 알로에향 화장실 담배 새집증후군 실내 집안 홀애비 옷장 냄새 제거, 300g, 1개",
   "photo_count": 0,
   "rating": 5,
   "user_name": "한*은"
  },
  {
   "answer": "",
   "content": "처음엔 향이 약한가 싶었는데, 며칠 지나니까 공간이 확 달라졌어요!!",
   "created_at": "2026.03.13",
   "headline": "",
   "helpful_count": 0,
   "option": "센트올 실내탈취제 알로에향 화장실 담배 새집증후군 실내 집안 홀애비 옷장 냄새 제거, 300g, 1개",
   "photo_count": 0,
   "rating": 5,
   "user_name": "허*유"
  },
  {
   "answer": "",
   "content": "화장실에 두었는데 냄새만 정리되고 향은 과하지 않아서 딱 좋아요!",
   "created_at": "2026.03.13",
   "headline": "",
   "helpful_count": 0,
   "option": "센트올 실내탈취제 알로에향 화장실 담배 새집증후군 실내 집안 홀애비 옷장 냄새 제거, 300g, 1개",
   "photo_count": 0,
   "rating": 5,
   "user_name": "윤*은"
  },
  {
   "answer": "",
   "content": "다른 향 사용해보고 만족스러워서 언센티드도 구매해봤습니다!",
   "created_at": "2026.03.13",
   "headline": "",
   "helpful_count": 0,
   "option": "센트올 실내탈취제 알로에향 화장실 담배 새집증후군 실내 집안 홀애비 옷장 냄새 제거, 300g, 1개",
   "photo_count": 0,
   "rating": 5,
   "user_name": "유*진"
  },
  {
   "answer": "",
   "content": "자취하면서 냄새 관리가 어려웠는데 이 제품 덕분에 훨씬 낫네요 ㅎㅎ",
   "created_at": "2026.03.13",
   "headline": "",
   "helpful_count": 0,
   "option": "센트올 실내탈취제 알로에향 화장실 담배 새집증후군 실내 집안 홀애비 옷장 냄새 제거, 300g, 1개",
   "photo_count": 0,
   "rating": 5,
   "user_name": "양*은"
  },
  {
   "answer": "",
   "content": "집에서 배달 음식먹고 나면 냄새 오래 남았는데 요즘은 덜합니다.",
   "created_at": "2026.03.13",
   "headline": "",
   "helpful_count": 0,
   "option": "센트올 실내탈취제 알로에향 화장실 담배 새집증후군 실내 집안 홀애비 옷장 냄새 제거, 300g, 1개",
   "photo_count": 0,
   "rating": 5,
   "user_name": "황*훈"
  },
  {
   "answer": "",
   "content": "냄새 때문에 집 들어올 때 기분이 별로였는데 요즘은 훨씬 좋네요.",
   "created_at": "2026.03.13",
   "headline": "",
   "helpful_count": 0,
   "option": "센트올 실내탈취제 알로에향 화장실 담배 새집증후군 실내 집안 홀애비 옷장 냄새 제거, 300g, 1개",
   "photo_count": 0,
   "rating": 5,
   "user_name": "안*율"
  },
  {
   "answer": "",
   "content": "공부방에 두었는데 향 때문에 집중 방해받는 일이 없어서 좋네요~",
   "created_at": "2026.03.13",
   "headline": "",
   "helpful_count": 0,
   "option": "센트올 실내탈취제 알로에향 화장실 담배 새집증후군 실내 집안 홀애비 옷장 냄새 제거, 300g, 1개",
   "photo_count": 0,
   "rating": 5,
   "user_name": "조*훈"
  },
  {
   "answer": "",
   "content": "집에 오래 있다 보면 냄새 때문에 답답했는데 요즘은 괜찮습니다.",
   "created_at": "2026.03.13",
   "headline": "",
   "helpful_count": 0,
   "option": "센트올 실내탈취제 알로에향 화장실 담배 새집증후군 실내 집안 홀애비 옷장 냄새 제거, 300g, 1개",
   "photo_count": 0,
   "rating": 5,
   "user_name": "장*준"
  },
  {
   "answer": "",
   "content": "향으로 확 덮는 게 아니라 은은하게 정리되는 타입! 이게 더 좋네요",
   "created_at": "2026.03.13",
   "headline": "",
   "helpful_count": 0,
   "option": "센트올 실내탈취제 알로에향 화장실 담배 새집증후군 실내 집안 홀애비 옷장 냄새 제거, 300g, 1개",
   "photo_count": 0,
   "rating": 5,
   "user_name": "문*윤"
  },
  {
   "answer": "",
   "content": "새집 냄새 때문에 샀는데 확실히 공기가 부드러워진 느낌이에요.",
   "created_at": "2026.03.13",
   "headline": "",
   "helpful_count": 0,
   "option": "센트올 실내탈취제 알로에향 화장실 담배 새집증후군 실내 집안 홀애비 옷장 냄새 제거, 300g, 1개",
   "photo_count": 0,
   "rating": 5,
   "user_name": "임*경"
  },
  {
   "answer": "",
   "content": "담배 냄새 때문에 스트레스였는데 확 올라오는 느낌이 줄었어요.",
   "created_at": "2026.03.13",
   "headline": "",
   "helpful_count": 0,
   "option": "센트올 실내탈취제 알로에향 화장실 담배 새집증후군 실내 집안 홀애비 옷장 냄새 제거, 300g, 1개",
   "photo_count": 0,
   "rating": 5,
   "user_name": "안*아"
  },
  {
   "answer": "",
   "content": "알로에 스킨 바른 것 같은 청결한 향이라 집 분위기랑 잘 어울려요.",
   "created_at": "2026.03.13",
   "headline": "",
   "helpful_count": 0,
   "option": "센트올 실내탈취제 알로에향 화장실 담배 새집증후군 실내 집안 홀애비 옷장 냄새 제거, 300g, 1개",
   "photo_count": 0,
   "rating": 5,
   "user_name": "정*율"
  },
  {
   "answer": "",
   "content": "알로에 느낌이라 그런지 답답하지 않고 시원한 느낌이 있어요.",
   "created_at": "2026.03.13",
   "headline": "",
   "helpful_count": 0,
   "option": "센트올 실내탈취제 알로에향 화장실 담배 새집증후군 실내 집안 홀애비 옷장 냄새 제거, 300g, 1개",
   "photo_count": 0,
   "rating": 5,
   "user_name": "윤*은"
  },
  {
   "answer": "",
   "content": "주방 쪽에 두었더니 음식을 하고 난 뒤 냄새가 덜 남는 것 같아요.",
   "created_at": "2026.03.13",
   "headline": "",
   "helpful_count": 0,
   "option": "센트올 실내탈취제 알로에향 화장실 담배 새집증후군 실내 집안 홀애비 옷장 냄새 제거, 300g, 1개",
   "photo_count": 0,
   "rating": 5,
   "user_name": "권*아"
  },
  {
   "answer": "",
   "content": "사무실 책상 옆에 두었는데 공간이 훨씬 쾌적하게 느껴지네용~ ^^",
   "created_at": "2026.03.13",
   "headline": "",
   "helpful_count": 0,
   "option": "센트올 실내탈취제 알로에향 화장실 담배 새집증후군 실내 집안 홀애비 옷장 냄새 제거, 300g, 1개",
   "photo_count": 0,
   "rating": 5,
   "user_name": "전*민"
  },
  {
   "answer": "",
   "content": "향이 강하지 않은 게 오히려 장점이에요. 오래 둬도 부담 없어요 ㅋㅋ",
   "created_at": "2026.03.13",
   "headline": "",
   "helpful_count": 0,
   "option": "센트올 실내탈취제 알로에향 화장실 담배 새집증후군 실내 집안 홀애비 옷장 냄새 제거, 300g, 1개",
   "photo_count": 0,
   "rating": 5,
   "user_name": "오*윤"
  },
  {
   "answer": "",
   "content": "아이 옷장에 두었는데 향이 배지 않아서 더 마음에 들더라구요!",
   "created_at": "2026.03.13",
   "headline": "",
   "helpful_count": 0,
   "option": "센트올 실내탈취제 알로에향 화장실 담배 새집증후군 실내 집안 홀애비 옷장 냄새 제거, 300g, 1개",
   "photo_count": 0,
   "rating": 5,
   "user_name": "오*원"
  },
  {
   "answer": "",
   "content": "아이 있는 집이라 걱정했는데 부담 없어서 계속 사용 중이에요 ㅎㅎ",
   "created_at": "2026.03.13",
   "headline": "",
   "helpful_count": 0,
   "option": "센트올 실내탈취제 알로에향 화장실 담배 새집증후군 실내 집안 홀애비 옷장 냄새 제거, 300g, 1개",
   "photo_count": 0,
   "rating": 5,
   "user_name": "정*진"
  },
  {
   "answer": "",
   "content": "냄새 덮는 방향제 보다 이런 은은한 탈취제 제품이 더 좋네요 ^^",
   "created_at": "2026.03.13",
   "headline": "",
   "helpful_count": 0,
   "option": "센트올 실내탈취제 알로에향 화장실 담배 새집증후군 실내 집안 홀애비 옷장 냄새 제거, 300g, 1개",
   "photo_count": 0,
   "rating": 5,
   "user_name": "문*윤"
  },
  {
   "answer": "",
   "content": "사춘기 아들방 필수템입니다&hellip; 말 안 해도 알죠?",
   "created_at": "2026.03.13",
   "headline": "",
   "helpful_count": 0,
   "option": "센트올 실내탈취제 알로에향 화장실 담배 새집증후군 실내 집안 홀애비 옷장 냄새 제거, 300g, 1개",
   "photo_count": 0,
   "rating": 5,
   "user_name": "전*서"
  },
  {
   "answer": "",
   "content": "처음엔 반신반의했는데 시더향 써보고 재구매까지 왔네요 ㅋㅋㅋ",
   "created_at": "2026.03.13",
   "headline": "",
   "helpful_count": 0,
   "option": "센트올 실내탈취제 알로에향 화장실 담배 새집증후군 실내 집안 홀애비 옷장 냄새 제거, 300g, 1개",
   "photo_count": 0,
   "rating": 5,
   "user_name": "임*원"
  },
  {
   "answer": "",
   "content": "향이 과하지 않아서 오래 둬도 부담 없어요. 이게 제일 큰 장점!",
   "created_at": "2026.03.13",
   "headline": "",
   "helpful_count": 0,
   "option": "센트올 실내탈취제 알로에향 화장실 담배 새집증후군 실내 집안 홀애비 옷장 냄새 제거, 300g, 1개",
   "photo_count": 0,
   "rating": 5,
   "user_name": "권*윤"
  },
  {
   "answer": "",
   "content": "은은한 알로에 느낌이라 편안하게 사용할 수 있더라구요 ㅎㅎ",
   "created_at": "2026.03.13",
   "headline": "",
   "helpful_count": 0,
   "option": "센트올 실내탈취제 알로에향 화장실 담배 새집증후군 실내 집안 홀애비 옷장 냄새 제거, 300g, 1개",
   "photo_count": 0,
   "rating": 5,
   "user_name": "권*진"
  },
  {
   "answer": "",
   "content": "신발장 위에 올려두고 쓰는데 공간이 훨씬 쾌적해졌어요.",
   "created_at": "2026.03.13",
   "headline": "",
   "helpful_count": 0,
   "option": "센트올 실내탈취제 알로에향 화장실 담배 새집증후군 실내 집안 홀애비 옷장 냄새 제거, 300g, 1개",
   "photo_count": 0,
   "rating": 5,
   "user_name": "최*서"
  },
  {
   "answer": "",
   "content": "집에 두자마자 공기가 깨끗해진 기분이에요! 기분 좋네요 ㅎㅎ",
   "created_at": "2026.03.13",
   "headline": "",
   "helpful_count": 0,
   "option": "센트올 실내탈취제 알로에향 화장실 담배 새집증후군 실내 집안 홀애비 옷장 냄새 제거, 300g, 1개",
   "photo_count": 0,
   "rating": 5,
   "user_name": "신*주"
  },
  {
   "answer": "",
   "content": "탈취력 때문에 재구매합니다!! 한 번 써본 사람은 알 듯 해요 ㅎㅎ",
   "created_at": "2026.03.13",
   "headline": "",
   "helpful_count": 0,
   "option": "센트올 실내탈취제 알로에향 화장실 담배 새집증후군 실내 집안 홀애비 옷장 냄새 제거, 300g, 1개",
   "photo_count": 0,
   "rating": 5,
   "user_name": "허*윤"
  },
  {
   "answer": "",
   "content": "고양이 모래 냄새 때문에 고민이었는데 확 줄어들었어요 ^^",
   "created_at": "2026.03.13",
   "headline": "",
   "helpful_count": 0,
   "option": "센트올 실내탈취제 알로에향 화장실 담배 새집증후군 실내 집안 홀애비 옷장 냄새 제거, 300g, 1개",
   "photo_count": 0,
   "rating": 5,
   "user_name": "신*서"
  },
  {
   "answer": "",
   "content": "냄새가 사라진다기보다 공기가 깨끗해지는 느낌입니다!",
   "created_at": "2026.03.13",
   "headline": "",
   "helpful_count": 0,
   "option": "센트올 실내탈취제 알로에향 화장실 담배 새집증후군 실내 집안 홀애비 옷장 냄새 제거, 300g, 1개",
   "photo_count": 0,
   "rating": 5,
   "user_name": "배*원"
  },
  {
   "answer": "",
   "content": "탈취 위주 제품이라 그런지 향이 과장되지 않아 좋습니다.",
   "created_at": "2026.03.13",
   "headline": "",
   "helpful_count": 0,
   "option": "센트올 실내탈취제 알로에향 화장실 담배 새집증후군 실내 집안 홀애비 옷장 냄새 제거, 300g, 1개",
   "photo_count": 0,
   "rating": 5,
   "user_name": "문*은"
  },
  {
   "answer": "",
   "content": "인위적인 느낌이 거의 없어서 만족도가 높은 제품이에요.",
   "created_at": "2026.03.13",
   "headline": "",
   "helpful_count": 0,
   "option": "센트올 실내탈취제 알로에향 화장실 담배 새집증후군 실내 집안 홀애비 옷장 냄새 제거, 300g, 1개",
   "photo_count": 0,
   "rating": 5,
   "user_name": "전*아"
  },
  {
   "answer": "",
   "content": "알로에 향이라 그런지 청량감이 있어서 답답함이 없어요.",
   "created_at": "2026.03.13",
   "headline": "",
   "helpful_count": 0,
   "option": "센트올 실내탈취제 알로에향 화장실 담배 새집증후군 실내 집안 홀애비 옷장 냄새 제거, 300g, 1개",
   "photo_count": 0,
   "rating": 5,
   "user_name": "박*은"
  },
  {
   "answer": "",
   "content": "기존에 쓰던 강한 향 제품보다 훨씬 편안한 느낌이에요~",
   "created_at": "2026.03.13",
   "headline": "",
   "helpful_count": 0,
   "option": "센트올 실내탈취제 알로에향 화장실 담배 새집증후군 실내 집안 홀애비 옷장 냄새 제거, 300g, 1개",
   "photo_count": 0,
   "rating": 5,
   "user_name": "신*진"
  },
  {
   "answer": "",
   "content": "집 냄새가 덜 올라오는 느낌이라 재구매 생각 중이에요 ㅎㅎ",
   "created_at": "2026.03.13",
   "headline": "",
   "helpful_count": 0,
   "option": "센트올 실내탈취제 알로에향 화장실 담배 새집증후군 실내 집안 홀애비 옷장 냄새 제거, 300g, 1개",
   "photo_count": 0,
   "rating": 5,
   "user_name": "고*경"
  },
  {
   "answer": "",
   "content": "향이 튀지 않아서 집 분위기랑 잘 어울려서 맘에 들어용 ㅋㅋ",
   "created_at": "2026.03.13",
   "headline": "",
   "helpful_count": 0,
   "option": "센트올 실내탈취제 알로에향 화장실 담배 새집증후군 실내 집안 홀애비 옷장 냄새 제거, 300g, 1개",
   "photo_count": 0,
   "rating": 5,
   "user_name": "허*윤"
  },
  {
   "answer": "",
   "content": "강한 방향제 싫어하는 분들께 추천하고 드리고 싶네요!!",
   "created_at": "2026.03.13",
   "headline": "",
   "helpful_count": 0,
   "option": "센트올 실내탈취제 알로에향 화장실 담배 새집증후군 실내 집안 홀애비 옷장 냄새 제거, 300g, 1개",
   "photo_count": 0,
   "rating": 5,
   "user_name": "오*은"
  },
  {
   "answer": "",
   "content": "집에서 생활하면서 냄새 신경 덜 쓰게 돼서 좋습니다.",
   "created_at": "2026.03.13",
   "headline": "",
   "helpful_count": 0,
   "option": "센트올 실내탈취제 알로에향 화장실 담배 새집증후군 실내 집안 홀애비 옷장 냄새 제거, 300g, 1개",
   "photo_count": 0,
   "rating": 5,
   "user_name": "홍*우"
  },
  {
   "answer": "",
   "content": "옷방에 두었더니 들어갈 때 꿉꿉한 느낌이 덜합니다.",
   "created_at": "2026.03.13",
   "headline": "",
   "helpful_count": 0,
   "option": "센트올 실내탈취제 알로에향 화장실 담배 새집증후군 실내 집안 홀애비 옷장 냄새 제거, 300g, 1개",
   "photo_count": 0,
   "rating": 5,
   "user_name": "임*윤"
  },
  {
   "answer": "",
   "content": "생각보다는 만족도가 높아서 계속 사용해보려구요.",
   "created_at": "2026.03.13",
   "headline": "",
   "helpful_count": 0,
   "option": "센트올 실내탈취제 알로에향 화장실 담배 새집증후군 실내 집안 홀애비 옷장 냄새 제거, 300g, 1개",
   "photo_count": 0,
   "rating": 5,
   "user_name": "홍*진"
  },
  {
   "answer": "",
   "content": "강한 향 싫어하는 사람들한테 추천합니다! 딱 좋아요",
   "created_at": "2026.03.13",
   "headline": "",
   "helpful_count": 0,
   "option": "센트올 실내탈취제 알로에향 화장실 담배 새집증후군 실내 집안 홀애비 옷장 냄새 제거, 300g, 1개",
   "photo_count": 0,
   "rating": 5,
   "user_name": "임*빈"
  },
  {
   "answer": "",
   "content": "은은하게 올라오는 향이 기분 전환이 되는거 같아용!",
   "created_at": "2026.03.13",
   "headline": "",
   "helpful_count": 0,
   "option": "센트올 실내탈취제 알로에향 화장실 담배 새집증후군 실내 집안 홀애비 옷장 냄새 제거, 300g, 1개",
   "photo_count": 0,
   "rating": 5,
   "user_name": "배*린"
  },
  {
   "answer": "",
   "content": "반려동물 키우는 집에도 부담이 없는 그런 향이에요 ㅎㅎ",
   "created_at": "2026.03.13",
   "headline": "",
   "helpful_count": 0,
   "option": "센트올 실내탈취제 알로에향 화장실 담배 새집증후군 실내 집안 홀애비 옷장 냄새 제거, 300g, 1개",
   "photo_count": 0,
   "rating": 5,
   "user_name": "허*윤"
  },
  {
   "answer": "",
   "content": "공간과 자연스럽게 어우러지는 향이라 좋았습니다.",
   "created_at": "2026.03.13",
   "headline": "",
   "helpful_count": 0,
   "option": "센트올 실내탈취제 알로에향 화장실 담배 새집증후군 실내 집안 홀애비 옷장 냄새 제거, 300g, 1개",
   "photo_count": 0,
   "rating": 5,
   "user_name": "조*아"
  },
  {
   "answer": "",
   "content": "신발장에 두니까 쿰쿰함이 정리되고 산뜻함만 남아요.",
   "created_at": "2026.03.12",
   "headline": "",
   "helpful_count": 0,
   "option": "센트올 실내탈취제 알로에향 화장실 담배 새집증후군 실내 집안 홀애비 옷장 냄새 제거, 300g, 1개",
   "photo_count": 0,
   "rating": 5,
   "user_name": "안*민"
  },
  {
   "answer": "",
   "content": "알로에 특유의 맑은 향이라 답답함이 전혀 없더라구요…!!",
   "created_at": "2026.03.12",
   "headline": "",
   "helpful_count": 0,
   "option": "센트올 실내탈취제 알로에향 화장실 담배 새집증후군 실내 집안 홀애비 옷장 냄새 제거, 300g, 1개",
   "photo_count": 0,
   "rating": 5,
   "user_name": "신*아"
  },
  {
   "answer": "",
   "content": "향이 진짜 자연적인 향이라 시원한 느낌도 들어요~",
   "created_at": "2026.03.17",
   "headline": "",
   "helpful_count": 0,
   "option": "센트올 실내탈취제 알로에향 화장실 담배 새집증후군 실내 집안 홀애비 옷장 냄새 제거, 300g, 1개",
   "photo_count": 0,
   "rating": 5,
   "user_name": "백*원"
  },
  {
   "answer": "",
   "content": "강한 방향제 싫어하는 분들한테 추천하고 싶네요~",
   "created_at": "2026.03.15",
   "headline": "",
   "helpful_count": 0,
   "option": "센트올 실내탈취제 알로에향 화장실 담배 새집증후군 실내 집안 홀애비 옷장 냄새 제거, 300g, 1개",
   "photo_count": 0,
   "rating": 5,
   "user_name": "손*인"
  },
  {
   "answer": "",
   "content": "신경 쓰이던 냄새가 자연스럽게 줄어들었네요 ^^",
   "created_at": "2026.03.15",
   "headline": "",
   "helpful_count": 0,
   "option": "센트올 실내탈취제 알로에향 화장실 담배 새집증후군 실내 집안 홀애비 옷장 냄새 제거, 300g, 1개",
   "photo_count": 0,
   "rating": 5,
   "user_name": "박*현"
  },
  {
   "answer": "",
   "content": "요리 후에 거실에 두니까 다음 날 훨씬 낫네요 ^_^",
   "created_at": "2026.03.13",
   "headline": "",
   "helpful_count": 0,
   "option": "센트올 실내탈취제 알로에향 화장실 담배 새집증후군 실내 집안 홀애비 옷장 냄새 제거, 300g, 1개",
   "photo_count": 0,
   "rating": 5,
   "user_name": "강*나"
  },
  {
   "answer": "",
   "content": "은은한 알로에 향이라 하루 종일 있어도 편안해요!",
   "created_at": "2026.03.13",
   "headline": "",
   "helpful_count": 0,
   "option": "센트올 실내탈취제 알로에향 화장실 담배 새집증후군 실내 집안 홀애비 옷장 냄새 제거, 300g, 1개",
   "photo_count": 0,
   "rating": 5,
   "user_name": "손*원"
  },
  {
   "answer": "",
   "content": "인테리어 해치지 않아서 좋아요. 탈취제 같지 않음!",
   "created_at": "2026.03.13",
   "headline": "",
   "helpful_count": 0,
   "option": "센트올 실내탈취제 알로에향 화장실 담배 새집증후군 실내 집안 홀애비 옷장 냄새 제거, 300g, 1개",
   "photo_count": 0,
   "rating": 5,
   "user_name": "한*나"
  },
  {
   "answer": "",
   "content": "산뜻한 향이 은은하게 유지돼서 만족스럽습니다!!",
   "created_at": "2026.03.13",
   "headline": "",
   "helpful_count": 0,
   "option": "센트올 실내탈취제 알로에향 화장실 담배 새집증후군 실내 집안 홀애비 옷장 냄새 제거, 300g, 1개",
   "photo_count": 0,
   "rating": 5,
   "user_name": "조*아"
  },
  {
   "answer": "",
   "content": "화장실에 두었는데 깨끗한 이미지가 더 살아나요 ㅎㅎ",
   "created_at": "2026.03.12",
   "headline": "",
   "helpful_count": 0,
   "option": "센트올 실내탈취제 알로에향 화장실 담배 새집증후군 실내 집안 홀애비 옷장 냄새 제거, 300g, 1개",
   "photo_count": 0,
   "rating": 5,
   "user_name": "안*진"
  },
  {
   "answer": "",
   "content": "방에 두니까 홀애비냄새가 덜 나는 느낌이에요!",
   "created_at": "2026.05.02",
   "headline": "",
   "helpful_count": 0,
   "option": "센트올 실내탈취제 알로에향 화장실 담배 새집증후군 실내 집안 홀애비 옷장 냄새 제거, 300g, 1개",
   "photo_count": 0,
   "rating": 5,
   "user_name": "심*은"
  },
  {
   "answer": "",
   "content": "화장실에 두고 나서 꿉꿉함이 덜 느껴져요.",
   "created_at": "2026.03.13",
   "headline": "",
   "helpful_count": 0,
   "option": "센트올 실내탈취제 알로에향 화장실 담배 새집증후군 실내 집안 홀애비 옷장 냄새 제거, 300g, 1개",
   "photo_count": 0,
   "rating": 5,
   "user_name": "손*윤"
  },
  {
   "answer": "",
   "content": "계절 상관없이 쓰기 무난한 향인 것 같아요!",
   "created_at": "2026.03.13",
   "headline": "",
   "helpful_count": 0,
   "option": "센트올 실내탈취제 알로에향 화장실 담배 새집증후군 실내 집안 홀애비 옷장 냄새 제거, 300g, 1개",
   "photo_count": 0,
   "rating": 5,
   "user_name": "조*나"
  },
  {
   "answer": "",
   "content": "거실 구석에 두고 사용 중인데 괜찮네요 ㅋㅋ",
   "created_at": "2026.03.13",
   "headline": "",
   "helpful_count": 0,
   "option": "센트올 실내탈취제 알로에향 화장실 담배 새집증후군 실내 집안 홀애비 옷장 냄새 제거, 300g, 1개",
   "photo_count": 0,
   "rating": 5,
   "user_name": "배*연"
  },
  {
   "answer": "",
   "content": "신발장 냄새 관리에 도움 되는 것 같아요.",
   "created_at": "2026.05.09",
   "headline": "",
   "helpful_count": 0,
   "option": "센트올 실내탈취제 알로에향 화장실 담배 새집증후군 실내 집안 홀애비 옷장 냄새 제거, 300g, 1개",
   "photo_count": 0,
   "rating": 5,
   "user_name": "남*우"
  },
  {
   "answer": "",
   "content": "옷장에 넣어두니 꿉꿉함이 줄어서 좋네요 ㅎㅎ",
   "created_at": "2026.05.13",
   "headline": "",
   "helpful_count": 0,
   "option": "센트올 실내탈취제 알로에향 화장실 담배 새집증후군 실내 집안 홀애비 옷장 냄새 제거, 300g, 1개",
   "photo_count": 0,
   "rating": 5,
   "user_name": "서*진"
  },
  {
   "answer": "",
   "content": "신발장에 두니까 꾸린내 냄새가 덜 올라옵니다.",
   "created_at": "2026.03.13",
   "headline": "",
   "helpful_count": 0,
   "option": "센트올 실내탈취제 알로에향 화장실 담배 새집증후군 실내 집안 홀애비 옷장 냄새 제거, 300g, 1개",
   "photo_count": 0,
   "rating": 5,
   "user_name": "송*현"
  },
  {
   "answer": "",
   "content": "알로에 향이라 그런지 시원하고 산뜻해요 ㅎㅎ",
   "created_at": "2026.03.13",
   "headline": "",
   "helpful_count": 0,
   "option": "센트올 실내탈취제 알로에향 화장실 담배 새집증후군 실내 집안 홀애비 옷장 냄새 제거, 300g, 1개",
   "photo_count": 0,
   "rating": 5,
   "user_name": "임*진"
  },
  {
   "answer": "",
   "content": "강한 향 싫어하는데 딱 제 취향이에요",
   "created_at": "2026.03.13",
   "headline": "",
   "helpful_count": 0,
   "option": "센트올 실내탈취제 알로에향 화장실 담배 새집증후군 실내 집안 홀애비 옷장 냄새 제거, 300g, 1개",
   "photo_count": 0,
   "rating": 5,
   "user_name": "전*나"
  },
  {
   "answer": "",
   "content": "향이 튀지 않아서 집 전체 분위기와 잘 어울려요.",
   "created_at": "2026.03.26",
   "headline": "",
   "helpful_count": 0,
   "option": "센트올 실내탈취제 알로에향 화장실 담배 새집증후군 실내 집안 홀애비 옷장 냄새 제거, 300g, 1개",
   "photo_count": 0,
   "rating": 5,
   "user_name": "류*우"
  },
  {
   "answer": "",
   "content": "집에 들어올 때 공기가 정리된 느낌이라 좋아요.",
   "created_at": "2026.03.13",
   "headline": "",
   "helpful_count": 0,
   "option": "센트올 실내탈취제 알로에향 화장실 담배 새집증후군 실내 집안 홀애비 옷장 냄새 제거, 300g, 1개",
   "photo_count": 0,
   "rating": 5,
   "user_name": "김*은"
  },
  {
   "answer": "",
   "content": "방 문 열 때마다 기분 좋아지는 향이에요!",
   "created_at": "2026.03.26",
   "headline": "",
   "helpful_count": 0,
   "option": "센트올 실내탈취제 알로에향 화장실 담배 새집증후군 실내 집안 홀애비 옷장 냄새 제거, 300g, 1개",
   "photo_count": 0,
   "rating": 5,
   "user_name": "장*린"
  },
  {
   "answer": "",
   "content": "향이 강하지 않아서 아이방에 두기 좋더라구요~",
   "created_at": "2026.03.13",
   "headline": "",
   "helpful_count": 0,
   "option": "센트올 실내탈취제 알로에향 화장실 담배 새집증후군 실내 집안 홀애비 옷장 냄새 제거, 300g, 1개",
   "photo_count": 0,
   "rating": 5,
   "user_name": "손*원"
  },
  {
   "answer": "",
   "content": "동물 특유 냄새가 섞이지 않고 정리돼서 좋네요.",
   "created_at": "2026.03.13",
   "headline": "",
   "helpful_count": 0,
   "option": "센트올 실내탈취제 알로에향 화장실 담배 새집증후군 실내 집안 홀애비 옷장 냄새 제거, 300g, 1개",
   "photo_count": 0,
   "rating": 5,
   "user_name": "손*린"
  },
  {
   "answer": "",
   "content": "은은하게 유지되는 향이라 거실에 잘 어울려용~",
   "created_at": "2026.03.26",
   "headline": "",
   "helpful_count": 0,
   "option": "센트올 실내탈취제 알로에향 화장실 담배 새집증후군 실내 집안 홀애비 옷장 냄새 제거, 300g, 1개",
   "photo_count": 0,
   "rating": 5,
   "user_name": "허*주"
  },
  {
   "answer": "",
   "content": "은은하게 퍼지는 알로에 향이 매력적인 느낌쓰~",
   "created_at": "2026.03.13",
   "headline": "",
   "helpful_count": 0,
   "option": "센트올 실내탈취제 알로에향 화장실 담배 새집증후군 실내 집안 홀애비 옷장 냄새 제거, 300g, 1개",
   "photo_count": 0,
   "rating": 5,
   "user_name": "조*주"
  },
  {
   "answer": "",
   "content": "탈취 기능과 향 균형이 잘 맞는 제품 같아요.",
   "created_at": "2026.03.13",
   "headline": "",
   "helpful_count": 0,
   "option": "센트올 실내탈취제 알로에향 화장실 담배 새집증후군 실내 집안 홀애비 옷장 냄새 제거, 300g, 1개",
   "photo_count": 0,
   "rating": 5,
   "user_name": "전*서"
  },
  {
   "answer": "",
   "content": "향이 무겁지 않아서 침실에 두기 괜찮았습니다.",
   "created_at": "2026.03.12",
   "headline": "",
   "helpful_count": 0,
   "option": "센트올 실내탈취제 알로에향 화장실 담배 새집증후군 실내 집안 홀애비 옷장 냄새 제거, 300g, 1개",
   "photo_count": 0,
   "rating": 5,
   "user_name": "홍*윤"
  },
  {
   "answer": "",
   "content": "맑은 느낌이라 공간이 더 정리된 것 같아요!",
   "created_at": "2026.03.13",
   "headline": "",
   "helpful_count": 0,
   "option": "센트올 실내탈취제 알로에향 화장실 담배 새집증후군 실내 집안 홀애비 옷장 냄새 제거, 300g, 1개",
   "photo_count": 0,
   "rating": 5,
   "user_name": "전*원"
  },
  {
   "answer": "",
   "content": "강한 방향제 싫어하는데 이 제품은 딱 좋네요!!",
   "created_at": "2026.03.13",
   "headline": "",
   "helpful_count": 0,
   "option": "센트올 실내탈취제 알로에향 화장실 담배 새집증후군 실내 집안 홀애비 옷장 냄새 제거, 300g, 1개",
   "photo_count": 0,
   "rating": 5,
   "user_name": "고*진"
  },
  {
   "answer": "",
   "content": "향이 강하지 않아서 너무 좋아요!",
   "created_at": "2026.05.13",
   "headline": "",
   "helpful_count": 0,
   "option": "센트올 실내탈취제 알로에향 화장실 담배 새집증후군 실내 집안 홀애비 옷장 냄새 제거, 300g, 1개",
   "photo_count": 0,
   "rating": 5,
   "user_name": "강*아"
  },
  {
   "answer": "",
   "content": "아랫집에서 담배를 피는지.. 밤마다 담배냄새 때문에 스트레스 받았는데 배란다에 두니까 냄새들이 많이 사라졌더라구요&hellip;",
   "created_at": "2026.03.26",
   "headline": "",
   "helpful_count": 0,
   "option": "센트올 실내탈취제 알로에향 화장실 담배 새집증후군 실내 집안 홀애비 옷장 냄새 제거, 300g, 1개",
   "photo_count": 0,
   "rating": 5,
   "user_name": "오*은"
  },
  {
   "answer": "",
   "content": "요즘 추워서 환기를 안시켰더니 방 안에 들어오면 이상한 냄새들이 나더라구요&hellip; 몇일 동안 테이블 위에 두었더니 방안에 냄새는 사라지고 공기가 좋아진 느낌이 들어요 ㅎㅎ",
   "created_at": "2026.03.13",
   "headline": "",
   "helpful_count": 0,
   "option": "센트올 실내탈취제 알로에향 화장실 담배 새집증후군 실내 집안 홀애비 옷장 냄새 제거, 300g, 1개",
   "photo_count": 0,
   "rating": 5,
   "user_name": "강*윤"
  },
  {
   "answer": "",
   "content": "산뜻한 향이 은근히 유지돼서 만족스러워서 주변에 추천해드렸어요 ㅎㅎ",
   "created_at": "2026.03.26",
   "headline": "",
   "helpful_count": 0,
   "option": "센트올 실내탈취제 알로에향 화장실 담배 새집증후군 실내 집안 홀애비 옷장 냄새 제거, 300g, 1개",
   "photo_count": 0,
   "rating": 5,
   "user_name": "유*우"
  },
  {
   "answer": "",
   "content": "알로에 향이라 그런지 청량감이 있어서 답답함이 없어요.",
   "created_at": "2026.03.26",
   "headline": "",
   "helpful_count": 0,
   "option": "센트올 실내탈취제 알로에향 화장실 담배 새집증후군 실내 집안 홀애비 옷장 냄새 제거, 300g, 1개",
   "photo_count": 0,
   "rating": 5,
   "user_name": "박*은"
  },
  {
   "answer": "",
   "content": "아이방에 두려고 샀는데 알로에처럼 깨끗한 향이라 괜찮네요.",
   "created_at": "2026.03.13",
   "headline": "",
   "helpful_count": 0,
   "option": "센트올 실내탈취제 알로에향 화장실 담배 새집증후군 실내 집안 홀애비 옷장 냄새 제거, 300g, 1개",
   "photo_count": 0,
   "rating": 5,
   "user_name": "황*린"
  },
  {
   "answer": "",
   "content": "냄새 잡으면서도 공기 자체가 산뜻해지는 느낌이에요.",
   "created_at": "2026.03.13",
   "headline": "",
   "helpful_count": 0,
   "option": "센트올 실내탈취제 알로에향 화장실 담배 새집증후군 실내 집안 홀애비 옷장 냄새 제거, 300g, 1개",
   "photo_count": 0,
   "rating": 5,
   "user_name": "임*원"
  },
  {
   "answer": "",
   "content": "향이 튀지 않아서 집 전체 분위기와 잘 어울려요.",
   "created_at": "2026.03.13",
   "headline": "",
   "helpful_count": 0,
   "option": "센트올 실내탈취제 알로에향 화장실 담배 새집증후군 실내 집안 홀애비 옷장 냄새 제거, 300g, 1개",
   "photo_count": 0,
   "rating": 5,
   "user_name": "류*우"
  },
  {
   "answer": "",
   "content": "방 문 열 때마다 기분 좋아지는 향이에요!",
   "created_at": "2026.03.13",
   "headline": "",
   "helpful_count": 0,
   "option": "센트올 실내탈취제 알로에향 화장실 담배 새집증후군 실내 집안 홀애비 옷장 냄새 제거, 300g, 1개",
   "photo_count": 0,
   "rating": 5,
   "user_name": "장*린"
  },
  {
   "answer": "",
   "content": "",
   "created_at": "2026.05.13",
   "headline": "",
   "helpful_count": 0,
   "option": "센트올 실내탈취제 알로에향 화장실 담배 새집증후군 실내 집안 홀애비 옷장 냄새 제거, 300g, 1개",
   "photo_count": 0,
   "rating": 5,
   "user_name": "전*림"
  },
  {
   "answer": "",
   "content": "",
   "created_at": "2026.05.05",
   "headline": "",
   "helpful_count": 0,
   "option": "센트올 실내탈취제 알로에향 화장실 담배 새집증후군 실내 집안 홀애비 옷장 냄새 제거, 300g, 1개",
   "photo_count": 0,
   "rating": 5,
   "user_name": "오*영"
  },
  {
   "answer": "",
   "content": "",
   "created_at": "2026.05.01",
   "headline": "",
   "helpful_count": 0,
   "option": "센트올 실내탈취제 알로에향 화장실 담배 새집증후군 실내 집안 홀애비 옷장 냄새 제거, 300g, 1개",
   "photo_count": 0,
   "rating": 5,
   "user_name": "신*주"
  },
  {
   "answer": "",
   "content": "",
   "created_at": "2026.04.11",
   "headline": "",
   "helpful_count": 0,
   "option": "센트올 실내탈취제 알로에향 화장실 담배 새집증후군 실내 집안 홀애비 옷장 냄새 제거, 300g, 1개",
   "photo_count": 0,
   "rating": 5,
   "user_name": "윤*나"
  },
  {
   "answer": "",
   "content": "",
   "created_at": "2026.04.10",
   "headline": "",
   "helpful_count": 0,
   "option": "센트올 실내탈취제 알로에향 화장실 담배 새집증후군 실내 집안 홀애비 옷장 냄새 제거, 300g, 4개",
   "photo_count": 0,
   "rating": 5,
   "user_name": "장*옥"
  },
  {
   "answer": "",
   "content": "",
   "created_at": "2026.04.09",
   "headline": "",
   "helpful_count": 0,
   "option": "센트올 실내탈취제 알로에향 화장실 담배 새집증후군 실내 집안 홀애비 옷장 냄새 제거, 300g, 1개",
   "photo_count": 0,
   "rating": 5,
   "user_name": "황*주"
  },
  {
   "answer": "",
   "content": "",
   "created_at": "2026.04.07",
   "headline": "",
   "helpful_count": 0,
   "option": "센트올 실내탈취제 알로에향 화장실 담배 새집증후군 실내 집안 홀애비 옷장 냄새 제거, 300g, 4개",
   "photo_count": 0,
   "rating": 5,
   "user_name": "배*연"
  },
  {
   "answer": "",
   "content": "",
   "created_at": "2026.03.08",
   "headline": "",
   "helpful_count": 0,
   "option": "센트올 실내탈취제 알로에향 화장실 담배 새집증후군 실내 집안 홀애비 옷장 냄새 제거, 300g, 1개",
   "photo_count": 0,
   "rating": 5,
   "user_name": "황*화"
  }
 ]
}